Workbook
Name activity: Ref!$N$3:$N$16
Name activity: Ref!$N$3:$N$16
Name activity: Ref!$N$3:$N$16
Name activity: Ref!$N$3:$N$16
Name budget: Ref!$P$3:$P$6
Name costCtr: Ref!$O$3:$O$35
Name costCtr: Ref!$O$3:$O$35
Name costCtr: Ref!$O$3:$O$35
Name costCtr: Ref!$O$3:$O$44
Name list1: '[1]Daily Accomplishment Report'!$F$12:$F$133
Name list1: '[2]DTR-Detailed'!$F$12:$F$133
Name list1: '[2]DTR-Detailed'!$F$12:$F$133
Name list1: DailyAccomplishmentReport!$S$12:$S$75
Name provider: Ref!$K$3:$K$6
Name provider: Ref!$K$3:$K$6
Name provider: Ref!$K$3:$K$6
Name provider: Ref!$K$3:$K$6
Name s: Ref!$O$3:$O$35
Name section: Ref!$M$3:$M$7
Name section: Ref!$M$3:$M$7
Name section: Ref!$M$3:$M$7
Name section: Ref!$M$3:$M$7
Name teamLead: Ref!$L$3:$L$7
Name teamLead: Ref!$L$3:$L$7
Name teamLead: Ref!$L$3:$L$7
Name teamLead: Ref!$L$3:$L$8

Sheet Instruction
B2: Instructions:
B3: In Daily Accomplishment Report worksheet, provide the following data:
B4: Name
B5: Provider (ex.: SLI, Radix)
B6: Team Lead
B7: Section/Unit
B8: Payroll Perion (To/From)
B9: Date(MM/DD/YY)
B10: Number of Hrs (Regular / OT)
C11: -Saturday, Sunday, Night Differential, Special Holiday(weekdays/Saturday/Sunday), Legal Holiday(weekedays/Saturday/Sunday)
B12: Cost Center
B13: Activity Type
B14: SIR
B15: Description
B16: In Attendance Report* worksheet, provide the following data:
B17: Position
B18: Time-In/Time-Out in Regulars (HH:MM) - required format is Military Time
B19: Time-In/Time-Out in Overtime (HH:MM) - required format is Military Time
B20: Other data are automatically populated or updated based on the value in Daily Accomplishment Report worksheet
B24: Legend:
C26: Weekdays
C27: Sunday
C28: Saturday
C29: Special Holidays (Mon-Sat)
C30: Beyond SH (Mon-Sat)
C31: Special Holidays(Sun)
C32: Beyond SH (Sun)
C33: Legal Holidays (Mon-Sat)
C34: Beyond LH (Mon-Sat)
C35: Legal Holidays(Sun)
C36: Beyond LH (Sun)
C37: Night Shift

Sheet DailyAccomplishmentReport
B1: DAILY TIME RECORD
B3: Name : | D3: MIKAELLA ANDREA DEVELOS
B4: Provider : | D4: RADIX
B5: Project Manager : | D5: Jun M. Salvanera
B6: Section/Unit : | D6: BD1
B7: Payroll Period : | D7: From | E7: To
D8: 11/16/25 | E8: 11/30/25 | G8: =DAY(D8) -> #VALUE!
AB9: 1.25 | AC9: 1.25 | AD9: 1.3 | AE9: 1.3 | AF9: 1.69 | AG9: 0.1 | AH9: 1.3 | AI9: 1.69 | AJ9: 1.5 | AK9: 1.95 | AL9: 2 | AM9: 2.6 | AN9: 2.6 | AO9: 3.38
B10: Date | C10: Number of Hours | E10: Saturday (OT) | F10: Saturday (OT>8) | G10: Sunday (OT) | H10: Sunday (OT>8) | I10: Night Diff (10PM - 6 AM) | J10: Special Holiday (<=8) | K10: Special Holiday (>8) | L10: Special Holiday (Sunday <=8) | M10: Special Holiday (Sunday > 8) | N10: Legal Holiday (<=8) | O10: Legal Holiday (>8) | P10: Legal Holiday (Sunday <=8) | Q10: Legal Holiday (Sunday > 8) | R10: SIR | S10: Cost Center | T10: Budget To Be Drawn Form | U10: Activity Type | V10: Description | AB10: Regular (OT > 8) | AC10: Saturday (OT) | AD10: Saturday (OT>8) | AE10: Sunday (OT) | AF10: Sunday (OT>8) | AG10: Night Diff (10PM - 6 AM) | AH10: Special Holiday (<=8) | AI10: Special Holiday (>8) | AJ10: Special Holiday (Sunday <=8) | AK10: Special Holiday (Sunday > 8) | AL10: Legal Holiday (<=8) | AM10: Legal Holiday (>8) | AN10: Legal Holiday (Sunday <=8) | AO10: Legal Holiday (Sunday > 8) | AP10: Total Hours
C11: Regular | D11: OT > 8 | X11: OT(%) | Y11: interest | Z11: day num
B12: 45962 | X12: =ROUND(D12*Y12,2) -> #N/A | Y12: =VLOOKUP(Z12,Ref!$C$3:$D$14,2,FALSE) -> #N/A | Z12: =VLOOKUP(B12,Ref!$F$3:$H$367,3,FALSE) -> #N/A | AB12: =(D12*$AB$9) -> 0 | AC12: =(E12*$AC$9) -> 0 | AD12: =(F12*$AD$9) -> 0 | AE12: =(G12*$AE$9) -> 0 | AF12: =(H12*$AF$9) -> 0 | AG12: =(I12*$AG$9) -> 0 | AH12: =(J12*$AH$9) -> 0 | AI12: =(K12*$AI$9) -> 0 | AJ12: =(L12*$AJ$9) -> 0 | AK12: =(M12*$AK$9) -> 0 | AL12: =(N12*$AL$9) -> 0 | AM12: =(O12*$AM$9) -> 0 | AN12: =(P12*$AN$9) -> 0 | AO12: =(Q12*$AO$9) -> 0 | AP12: =SUM(AB12:AO12) -> 0
B13: 45963 | X13: =ROUND(D13*Y13,2) -> #N/A | Y13: =VLOOKUP(Z13,Ref!$C$3:$D$14,2,FALSE) -> #N/A | Z13: =VLOOKUP(B13,Ref!$F$3:$H$367,3,FALSE) -> #N/A | AB13: =(D13*$AB$9) -> 0 | AC13: =(E13*$AC$9) -> 0 | AD13: =(F13*$AD$9) -> 0 | AE13: =(G13*$AE$9) -> 0 | AF13: =(H13*$AF$9) -> 0 | AG13: =(I13*$AG$9) -> 0 | AH13: =(J13*$AH$9) -> 0 | AI13: =(K13*$AI$9) -> 0 | AJ13: =(L13*$AJ$9) -> 0 | AK13: =(M13*$AK$9) -> 0 | AL13: =(N13*$AL$9) -> 0 | AM13: =(O13*$AM$9) -> 0 | AN13: =(P13*$AN$9) -> 0 | AO13: =(Q13*$AO$9) -> 0 | AP13: =SUM(AB13:AO13) -> 0
B14: 45964 | C14: 8 | S14: OP - IT | V14: Worked on billers module frontend, connecting forms and validation logic. | X14: =ROUND(D14*Y14,2) -> #N/A | Y14: =VLOOKUP(Z14,Ref!$C$3:$D$14,2,FALSE) -> #N/A | Z14: =VLOOKUP(B14,Ref!$F$3:$H$367,3,FALSE) -> #N/A | AB14: =(D14*$AB$9) -> 0 | AC14: =(E14*$AC$9) -> 0 | AD14: =(F14*$AD$9) -> 0 | AE14: =(G14*$AE$9) -> 0 | AF14: =(H14*$AF$9) -> 0 | AG14: =(I14*$AG$9) -> 0 | AH14: =(J14*$AH$9) -> 0 | AI14: =(K14*$AI$9) -> 0 | AJ14: =(L14*$AJ$9) -> 0 | AK14: =(M14*$AK$9) -> 0 | AL14: =(N14*$AL$9) -> 0 | AM14: =(O14*$AM$9) -> 0 | AN14: =(P14*$AN$9) -> 0 | AO14: =(Q14*$AO$9) -> 0 | AP14: =SUM(AB14:AO14) -> 0
B15: 45965 | C15: 8 | S15: OP - IT | V15: Worked on billers module frontend, connecting forms and validation logic. | X15: =ROUND(D15*Y15,2) -> #N/A | Y15: =VLOOKUP(Z15,Ref!$C$3:$D$14,2,FALSE) -> #N/A | Z15: =VLOOKUP(B15,Ref!$F$3:$H$367,3,FALSE) -> #N/A | AB15: =(D15*$AB$9) -> 0 | AC15: =(E15*$AC$9) -> 0 | AD15: =(F15*$AD$9) -> 0 | AE15: =(G15*$AE$9) -> 0 | AF15: =(H15*$AF$9) -> 0 | AG15: =(I15*$AG$9) -> 0 | AH15: =(J15*$AH$9) -> 0 | AI15: =(K15*$AI$9) -> 0 | AJ15: =(L15*$AJ$9) -> 0 | AK15: =(M15*$AK$9) -> 0 | AL15: =(N15*$AL$9) -> 0 | AM15: =(O15*$AM$9) -> 0 | AN15: =(P15*$AN$9) -> 0 | AO15: =(Q15*$AO$9) -> 0 | AP15: =SUM(AB15:AO15) -> 0
B16: 45966 | C16: 8 | S16: OP - IT | V16: Began coding the frontend components for the dashboard, setting up initial UI elements. | X16: =ROUND(D16*Y16,2) -> #N/A | Y16: =VLOOKUP(Z16,Ref!$C$3:$D$14,2,FALSE) -> #N/A | Z16: =VLOOKUP(B16,Ref!$F$3:$H$367,3,FALSE) -> #N/A | AB16: =(D16*$AB$9) -> 0 | AC16: =(E16*$AC$9) -> 0 | AD16: =(F16*$AD$9) -> 0 | AE16: =(G16*$AE$9) -> 0 | AF16: =(H16*$AF$9) -> 0 | AG16: =(I16*$AG$9) -> 0 | AH16: =(J16*$AH$9) -> 0 | AI16: =(K16*$AI$9) -> 0 | AJ16: =(L16*$AJ$9) -> 0 | AK16: =(M16*$AK$9) -> 0 | AL16: =(N16*$AL$9) -> 0 | AM16: =(O16*$AM$9) -> 0 | AN16: =(P16*$AN$9) -> 0 | AO16: =(Q16*$AO$9) -> 0 | AP16: =SUM(AB16:AO16) -> 0
B17: 45967 | C17: 8 | S17: OP - IT | V17: Worked on billers module frontend, connecting forms and validation logic. | X17: =ROUND(D17*Y17,2) -> #N/A | Y17: =VLOOKUP(Z17,Ref!$C$3:$D$14,2,FALSE) -> #N/A | Z17: =VLOOKUP(B17,Ref!$F$3:$H$367,3,FALSE) -> #N/A | AB17: =(D17*$AB$9) -> 0 | AC17: =(E17*$AC$9) -> 0 | AD17: =(F17*$AD$9) -> 0 | AE17: =(G17*$AE$9) -> 0 | AF17: =(H17*$AF$9) -> 0 | AG17: =(I17*$AG$9) -> 0 | AH17: =(J17*$AH$9) -> 0 | AI17: =(K17*$AI$9) -> 0 | AJ17: =(L17*$AJ$9) -> 0 | AK17: =(M17*$AK$9) -> 0 | AL17: =(N17*$AL$9) -> 0 | AM17: =(O17*$AM$9) -> 0 | AN17: =(P17*$AN$9) -> 0 | AO17: =(Q17*$AO$9) -> 0 | AP17: =SUM(AB17:AO17) -> 0
B18: 45968 | C18: 8 | S18: OP - IT | V18: Working on PDF CDeveloped frontend modules for the attendance feature, ensuring usability and accuracy.onverter reseach and implementation how to convert docx to pdf | X18: =ROUND(D18*Y18,2) -> #N/A | Y18: =VLOOKUP(Z18,Ref!$C$3:$D$14,2,FALSE) -> #N/A | Z18: =VLOOKUP(B18,Ref!$F$3:$H$367,3,FALSE) -> #N/A | AB18: =(D18*$AB$9) -> 0 | AC18: =(E18*$AC$9) -> 0 | AD18: =(F18*$AD$9) -> 0 | AE18: =(G18*$AE$9) -> 0 | AF18: =(H18*$AF$9) -> 0 | AG18: =(I18*$AG$9) -> 0 | AH18: =(J18*$AH$9) -> 0 | AI18: =(K18*$AI$9) -> 0 | AJ18: =(L18*$AJ$9) -> 0 | AK18: =(M18*$AK$9) -> 0 | AL18: =(N18*$AL$9) -> 0 | AM18: =(O18*$AM$9) -> 0 | AN18: =(P18*$AN$9) -> 0 | AO18: =(Q18*$AO$9) -> 0 | AP18: =SUM(AB18:AO18) -> 0
B19: 45969 | X19: =ROUND(D19*Y19,2) -> #N/A | Y19: =VLOOKUP(Z19,Ref!$C$3:$D$14,2,FALSE) -> #N/A | Z19: =VLOOKUP(B19,Ref!$F$3:$H$367,3,FALSE) -> #N/A | AB19: =(D19*$AB$9) -> 0 | AC19: =(E19*$AC$9) -> 0 | AD19: =(F19*$AD$9) -> 0 | AE19: =(G19*$AE$9) -> 0 | AF19: =(H19*$AF$9) -> 0 | AG19: =(I19*$AG$9) -> 0 | AH19: =(J19*$AH$9) -> 0 | AI19: =(K19*$AI$9) -> 0 | AJ19: =(L19*$AJ$9) -> 0 | AK19: =(M19*$AK$9) -> 0 | AL19: =(N19*$AL$9) -> 0 | AM19: =(O19*$AM$9) -> 0 | AN19: =(P19*$AN$9) -> 0 | AO19: =(Q19*$AO$9) -> 0 | AP19: =SUM(AB19:AO19) -> 0
B20: 45970 | X20: =ROUND(D20*Y20,2) -> #N/A | Y20: =VLOOKUP(Z20,Ref!$C$3:$D$14,2,FALSE) -> #N/A | Z20: =VLOOKUP(B20,Ref!$F$3:$H$367,3,FALSE) -> #N/A | AB20: =(D20*$AB$9) -> 0 | AC20: =(E20*$AC$9) -> 0 | AD20: =(F20*$AD$9) -> 0 | AE20: =(G20*$AE$9) -> 0 | AF20: =(H20*$AF$9) -> 0 | AG20: =(I20*$AG$9) -> 0 | AH20: =(J20*$AH$9) -> 0 | AI20: =(K20*$AI$9) -> 0 | AJ20: =(L20*$AJ$9) -> 0 | AK20: =(M20*$AK$9) -> 0 | AL20: =(N20*$AL$9) -> 0 | AM20: =(O20*$AM$9) -> 0 | AN20: =(P20*$AN$9) -> 0 | AO20: =(Q20*$AO$9) -> 0 | AP20: =SUM(AB20:AO20) -> 0
B21: 45971 | X21: =ROUND(D21*Y21,2) -> #N/A | Y21: =VLOOKUP(Z21,Ref!$C$3:$D$14,2,FALSE) -> #N/A | Z21: =VLOOKUP(B21,Ref!$F$3:$H$367,3,FALSE) -> #N/A | AB21: =(D21*$AB$9) -> 0 | AC21: =(E21*$AC$9) -> 0 | AD21: =(F21*$AD$9) -> 0 | AE21: =(G21*$AE$9) -> 0 | AF21: =(H21*$AF$9) -> 0 | AG21: =(I21*$AG$9) -> 0 | AH21: =(J21*$AH$9) -> 0 | AI21: =(K21*$AI$9) -> 0 | AJ21: =(L21*$AJ$9) -> 0 | AK21: =(M21*$AK$9) -> 0 | AL21: =(N21*$AL$9) -> 0 | AM21: =(O21*$AM$9) -> 0 | AN21: =(P21*$AN$9) -> 0 | AO21: =(Q21*$AO$9) -> 0 | AP21: =SUM(AB21:AO21) -> 0
B22: 45972 | C22: 8 | S22: OP - IT | V22: Worked on billers module frontend, connecting forms and validation logic. | X22: =ROUND(D22*Y22,2) -> #N/A | Y22: =VLOOKUP(Z22,Ref!$C$3:$D$14,2,FALSE) -> #N/A | Z22: =VLOOKUP(B22,Ref!$F$3:$H$367,3,FALSE) -> #N/A | AB22: =(D22*$AB$9) -> 0 | AC22: =(E22*$AC$9) -> 0 | AD22: =(F22*$AD$9) -> 0 | AE22: =(G22*$AE$9) -> 0 | AF22: =(H22*$AF$9) -> 0 | AG22: =(I22*$AG$9) -> 0 | AH22: =(J22*$AH$9) -> 0 | AI22: =(K22*$AI$9) -> 0 | AJ22: =(L22*$AJ$9) -> 0 | AK22: =(M22*$AK$9) -> 0 | AL22: =(N22*$AL$9) -> 0 | AM22: =(O22*$AM$9) -> 0 | AN22: =(P22*$AN$9) -> 0 | AO22: =(Q22*$AO$9) -> 0 | AP22: =SUM(AB22:AO22) -> 0
B23: 45973 | C23: 5.83 | S23: OP - IT | V23: Adjusted and fixed backend issues | X23: =ROUND(D23*Y23,2) -> #N/A | Y23: =VLOOKUP(Z23,Ref!$C$3:$D$14,2,FALSE) -> #N/A | Z23: =VLOOKUP(B23,Ref!$F$3:$H$367,3,FALSE) -> #N/A | AB23: =(D23*$AB$9) -> 0 | AC23: =(E23*$AC$9) -> 0 | AD23: =(F23*$AD$9) -> 0 | AE23: =(G23*$AE$9) -> 0 | AF23: =(H23*$AF$9) -> 0 | AG23: =(I23*$AG$9) -> 0 | AH23: =(J23*$AH$9) -> 0 | AI23: =(K23*$AI$9) -> 0 | AJ23: =(L23*$AJ$9) -> 0 | AK23: =(M23*$AK$9) -> 0 | AL23: =(N23*$AL$9) -> 0 | AM23: =(O23*$AM$9) -> 0 | AN23: =(P23*$AN$9) -> 0 | AO23: =(Q23*$AO$9) -> 0 | AP23: =SUM(AB23:AO23) -> 0
B24: 45974 | C24: 8 | S24: OP - IT | V24: Finalized backend adjustments | X24: =ROUND(D24*Y24,2) -> #N/A | Y24: =VLOOKUP(Z24,Ref!$C$3:$D$14,2,FALSE) -> #N/A | Z24: =VLOOKUP(B24,Ref!$F$3:$H$367,3,FALSE) -> #N/A | AB24: =(D24*$AB$9) -> 0 | AC24: =(E24*$AC$9) -> 0 | AD24: =(F24*$AD$9) -> 0 | AE24: =(G24*$AE$9) -> 0 | AF24: =(H24*$AF$9) -> 0 | AG24: =(I24*$AG$9) -> 0 | AH24: =(J24*$AH$9) -> 0 | AI24: =(K24*$AI$9) -> 0 | AJ24: =(L24*$AJ$9) -> 0 | AK24: =(M24*$AK$9) -> 0 | AL24: =(N24*$AL$9) -> 0 | AM24: =(O24*$AM$9) -> 0 | AN24: =(P24*$AN$9) -> 0 | AO24: =(Q24*$AO$9) -> 0 | AP24: =SUM(AB24:AO24) -> 0
B25: 45975 | C25: 8 | S25: OP - IT | V25: Conducted thorough debugging across modules | X25: =ROUND(D25*Y25,2) -> #N/A | Y25: =VLOOKUP(Z25,Ref!$C$3:$D$14,2,FALSE) -> #N/A | Z25: =VLOOKUP(B25,Ref!$F$3:$H$367,3,FALSE) -> #N/A | AB25: =(D25*$AB$9) -> 0 | AC25: =(E25*$AC$9) -> 0 | AD25: =(F25*$AD$9) -> 0 | AE25: =(G25*$AE$9) -> 0 | AF25: =(H25*$AF$9) -> 0 | AG25: =(I25*$AG$9) -> 0 | AH25: =(J25*$AH$9) -> 0 | AI25: =(K25*$AI$9) -> 0 | AJ25: =(L25*$AJ$9) -> 0 | AK25: =(M25*$AK$9) -> 0 | AL25: =(N25*$AL$9) -> 0 | AM25: =(O25*$AM$9) -> 0 | AN25: =(P25*$AN$9) -> 0 | AO25: =(Q25*$AO$9) -> 0 | AP25: =SUM(AB25:AO25) -> 0
B26: 45976 | X26: =ROUND(D26*Y26,2) -> #N/A | Y26: =VLOOKUP(Z26,Ref!$C$3:$D$14,2,FALSE) -> #N/A | Z26: =VLOOKUP(B26,Ref!$F$3:$H$367,3,FALSE) -> #N/A | AB26: =(D26*$AB$9) -> 0 | AC26: =(E26*$AC$9) -> 0 | AD26: =(F26*$AD$9) -> 0 | AE26: =(G26*$AE$9) -> 0 | AF26: =(H26*$AF$9) -> 0 | AG26: =(I26*$AG$9) -> 0 | AH26: =(J26*$AH$9) -> 0 | AI26: =(K26*$AI$9) -> 0 | AJ26: =(L26*$AJ$9) -> 0 | AK26: =(M26*$AK$9) -> 0 | AL26: =(N26*$AL$9) -> 0 | AM26: =(O26*$AM$9) -> 0 | AN26: =(P26*$AN$9) -> 0 | AO26: =(Q26*$AO$9) -> 0 | AP26: =SUM(AB26:AO26) -> 0
B27: 45977
B28: 45978 | C28: 8 | S28: OP - IT | V28: Worked on billers module frontend, connecting forms and validation logic.
B29: 45979 | C29: 8 | S29: OP - IT | V29: Worked on billers module frontend, connecting forms and validation logic.
B30: 45980 | C30: 8 | S30: OP - IT | V30: Worked on billers module frontend, connecting forms and validation logic.
B31: 45981 | C31: 8 | S31: OP - IT | V31: Assisted instapay testing
B32: 45982 | C32: 8 | S32: OP - IT | V32: Assisted instapay testing
B33: 45983
B34: 45984
B35: 45985 | C35: 8 | S35: OP - IT | V35: Worked on instapay dashboard
B36: 45986 | C36: 8 | S36: OP - IT | V36: assisted euronet and instapay testing
B37: 45987 | C37: 8 | S37: OP - IT | V37: assisted euronet and instapay testing
B38: 11/27/25 | C38: 8 | S38: OP - IT | V38: assisted euronet and instapay testing
B39: 11/28/25 | C39: 7 | S39: OP - IT | V39: Worked on instapay dashboard's error
B40: 11/29/25
B41: 11/30/25
B44: Total | C44: =SUM(C12:C43) -> 148.83 | D44: =SUM(D12:D43) -> 0 | E44: =SUM(E12:E43) -> 0 | F44: =SUM(F12:F43) -> 0 | G44: =SUM(G12:G43) -> 0 | H44: =SUM(H12:H43) -> 0 | I44: =SUM(I12:I43) -> 0 | J44: =SUM(J12:J43) -> 0 | ... Q44: =SUM(Q12:Q43) -> 0 | S44: Group Human Capital
S45: OP - Audit
S46: OP - Risk Mgmnt
S47: OP - Credit Mgmnt
S48: OP - IT
S49: RBG - BE
S50: RBG - QA
S51: RBG - Business Dev
S52: RBG - VB
S53: RBG - Auto
S54: RBG - Mortgage
S55: RBG - LAD(P/S)
S56: RBG - Cards
... S75: GB - REF

Sheet Attendance Report__First
B1: RADIX
B4: Name | D4: Mikaella Andrea Develos
B5: Shift Schedule | D5: 0.35416667 | E5: 0.72916667 | F5: 0.00069444444 | G5: =E5-F5 -> 0.72847222
B6: Client | D6: Maybank Phil. Inc.
B7: Payroll Period | D7: From | E7: To
D8: 45962 | E8: 45976 | F8: 0.25
E9: 0.91666667 | F9: 1
B10: Date | C10: Regular Hrs | E10: Overtime | G10: Total Hrs | I10: Remarks
C11: In | D11: Out | E11: In | F11: Out | G11: Regular | H11: OT | AB11: Night Diff | AC11: 0.1 | AD11: OTs | AE11: Int(%) | AF11: OT Total
B12: =D8 -> 45962 | G12: =IF(AND(C12="",D12=""),"",IF(AND(C12<=$D$5,D12>=$E$5),8, IF(AND(Q12<4,Q12>0,R12>=0),8-S12,IF(AND(Q12<4,C12>$D$5,U12>5),T12-(S12+1), IF(AND(Q12>3,D12<$E$5),T12-S12,IF(AND(Q12>3,D12>=$E$5),9-S12,IF(AND(C12>$D$5,U12<=4),T12-S12,IF(AND(C12>$D$5,U12>4),U12-(S12+1),IF(AND(C12<=$D$5,U12>=5),T12-1,IF(AND(C12<=$D$5,T12<=4),T12,IF(AND(C12<=$D$5,T12<5),4,IF(U12>5,U12-1,IF(U12<=4,U12,0))))))))))))) | H12: =IF(F12-E12*24=0,"",IF(ROUND((F12-E12)*24,2)>=6,ROUND((F12-E12)*24,2)-1,ROUND((F12-E12)*24,2))) | K12: =Billing!C37 -> 0 | L12: =Billing!D37 -> 0 | M12: ='Attendance Report - Manager'!G27 -> 0 | N12: ='Attendance Report - Manager'!H27 -> 0 | P12: =SUMIF(DailyAccomplishmentReport!$B$12:$B$26,B12,DailyAccomplishmentReport!$AP$12:$AP$26) -> 0 | Q12: =IF(C12<>"", (C12-$D$5)*24,0) -> 0 | R12: =IF(D12<>"", (D12-$E$5)*24,0) -> 0 | S12: =(ROUNDUP(Q12/0.5,0)*0.5 ) -> 0 | T12: =ROUND((D12-$D$5)*24,2) -> -8.5 | U12: =(D12-C12)*24 -> 0 | Z12: =VLOOKUP(B12,Ref!$F$3:$H$367,3,FALSE) -> #N/A | AA12: =SUMIF(DailyAccomplishmentReport!$B$12:$B$43,B12,DailyAccomplishmentReport!$D$12:$D$43) -> 0 | AB12: =IF(F12=$F$9,2,IF(AND(E12>=0,F12<=$F$8),(F12-E12)*24,IF(F12>$E$9,(F12-$E$9)*24,0))) -> 0 | AC12: =ROUND(AB12*$AC$11,2) -> 0 | AD12: =ROUND((F12-E12)*24,2) -> 0 | AE12: =VLOOKUP(Z12,Ref!$C$3:$D$14,2,) -> #N/A | AF12: =AD12*AE12 -> #N/A
B13: =B12+1 -> 45963 | G13: =IF(AND(C13="",D13=""),"",IF(AND(C13<=$D$5,D13>=$E$5),8, IF(AND(Q13<4,Q13>0,R13>=0),8-S13,IF(AND(Q13<4,C13>$D$5,U13>5),T13-(S13+1), IF(AND(Q13>3,D13<$E$5),T13-S13,IF(AND(Q13>3,D13>=$E$5),9-S13,IF(AND(C13>$D$5,U13<=4),T13-S13,IF(AND(C13>$D$5,U13>4),U13-(S13+1),IF(AND(C13<=$D$5,U13>=5),T13-1,IF(AND(C13<=$D$5,T13<=4),T13,IF(AND(C13<=$D$5,T13<5),4,IF(U13>5,U13-1,IF(U13<=4,U13,0))))))))))))) | H13: =IF(F13-E13*24=0,"",IF(ROUND((F13-E13)*24,2)>=6,ROUND((F13-E13)*24,2)-1,ROUND((F13-E13)*24,2))) | K13: =Billing!C38 -> 0 | L13: =Billing!D38 -> 0 | M13: ='Attendance Report - Manager'!G28 -> 0 | N13: ='Attendance Report - Manager'!H28 -> 0 | P13: =SUMIF(DailyAccomplishmentReport!$B$12:$B$26,B13,DailyAccomplishmentReport!$AP$12:$AP$26) -> 0 | Q13: =IF(C13<>"", (C13-$D$5)*24,0) -> 0 | R13: =IF(D13<>"", (D13-$E$5)*24,0) -> 0 | S13: =(ROUNDUP(Q13/0.5,0)*0.5 ) -> 0 | T13: =ROUND((D13-$D$5)*24,2) -> -8.5 | U13: =(D13-C13)*24 -> 0 | Z13: =VLOOKUP(B13,Ref!$F$3:$H$367,3,FALSE) -> #N/A | AA13: =SUMIF(DailyAccomplishmentReport!$B$12:$B$43,B13,DailyAccomplishmentReport!$D$12:$D$43) -> 0 | AB13: =IF(F13=$F$9,2,IF(AND(E13>=0,F13<=$F$8),(F13-E13)*24,IF(F13>$E$9,(F13-$E$9)*24,0))) -> 0 | AC13: =ROUND(AB13*$AC$11,2) -> 0 | AD13: =ROUND((F13-E13)*24,2) -> 0 | AE13: =VLOOKUP(Z13,Ref!$C$3:$D$14,2,) -> #N/A | AF13: =AD13*AE13 -> #N/A
B14: =B13+1 -> 45964 | C14: 0.32361111 | D14: 0.73263889 | G14: =IF(AND(C14="",D14=""),"",IF(AND(C14<=$D$5,D14>=$E$5),8, IF(AND(Q14<4,Q14>0,R14>=0),8-S14,IF(AND(Q14<4,C14>$D$5,U14>5),T14-(S14+1), IF(AND(Q14>3,D14<$E$5),T14-S14,IF(AND(Q14>3,D14>=$E$5),9-S14,IF(AND(C14>$D$5,U14<=4),T14-S14,IF(AND(C14>$D$5,U14>4),U14-(S14+1),IF(AND(C14<=$D$5,U14>=5),T14-1,IF(AND(C14<=$D$5,T14<=4),T14,IF(AND(C14<=$D$5,T14<5),4,IF(U14>5,U14-1,IF(U14<=4,U14,0))))))))))))) -> 8 | H14: =IF(F14-E14*24=0,"",IF(ROUND((F14-E14)*24,2)>=6,ROUND((F14-E14)*24,2)-1,ROUND((F14-E14)*24,2))) | I14: Worked on billers module frontend, connecting forms and validation logic. | K14: =Billing!C39 -> 0 | L14: =Billing!D39 -> 0 | M14: ='Attendance Report - Manager'!G29 -> 8 | N14: ='Attendance Report - Manager'!H29 -> 0 | P14: =SUMIF(DailyAccomplishmentReport!$B$12:$B$26,B14,DailyAccomplishmentReport!$AP$12:$AP$26) -> 0 | Q14: =IF(C14<>"", (C14-$D$5)*24,0) -> -0.73333333 | R14: =IF(D14<>"", (D14-$E$5)*24,0) -> 0.083333333 | S14: =(ROUNDUP(Q14/0.5,0)*0.5 ) -> -1 | T14: =ROUND((D14-$D$5)*24,2) -> 9.08 | U14: =(D14-C14)*24 -> 9.8166667 | Z14: =VLOOKUP(B14,Ref!$F$3:$H$367,3,FALSE) -> #N/A | AA14: =SUMIF(DailyAccomplishmentReport!$B$12:$B$43,B14,DailyAccomplishmentReport!$D$12:$D$43) -> 0 | AB14: =IF(F14=$F$9,2,IF(AND(E14>=0,F14<=$F$8),(F14-E14)*24,IF(F14>$E$9,(F14-$E$9)*24,0))) -> 0 | AC14: =ROUND(AB14*$AC$11,2) -> 0 | AD14: =ROUND((F14-E14)*24,2) -> 0 | AE14: =VLOOKUP(Z14,Ref!$C$3:$D$14,2,) -> #N/A | AF14: =AD14*AE14 -> #N/A
B15: =B14+1 -> 45965 | C15: 0.33819444 | D15: 0.73125 | G15: =IF(AND(C15="",D15=""),"",IF(AND(C15<=$D$5,D15>=$E$5),8, IF(AND(Q15<4,Q15>0,R15>=0),8-S15,IF(AND(Q15<4,C15>$D$5,U15>5),T15-(S15+1), IF(AND(Q15>3,D15<$E$5),T15-S15,IF(AND(Q15>3,D15>=$E$5),9-S15,IF(AND(C15>$D$5,U15<=4),T15-S15,IF(AND(C15>$D$5,U15>4),U15-(S15+1),IF(AND(C15<=$D$5,U15>=5),T15-1,IF(AND(C15<=$D$5,T15<=4),T15,IF(AND(C15<=$D$5,T15<5),4,IF(U15>5,U15-1,IF(U15<=4,U15,0))))))))))))) -> 8 | H15: =IF(F15-E15*24=0,"",IF(ROUND((F15-E15)*24,2)>=6,ROUND((F15-E15)*24,2)-1,ROUND((F15-E15)*24,2))) | I15: Worked on billers module frontend, connecting forms and validation logic. | K15: =Billing!C40 -> 0 | L15: =Billing!D40 -> 0 | M15: ='Attendance Report - Manager'!G30 -> 8 | N15: ='Attendance Report - Manager'!H30 -> 0 | P15: =SUMIF(DailyAccomplishmentReport!$B$12:$B$26,B15,DailyAccomplishmentReport!$AP$12:$AP$26) -> 0 | Q15: =IF(C15<>"", (C15-$D$5)*24,0) -> -0.38333333 | R15: =IF(D15<>"", (D15-$E$5)*24,0) -> 0.05 | S15: =(ROUNDUP(Q15/0.5,0)*0.5 ) -> -0.5 | T15: =ROUND((D15-$D$5)*24,2) -> 9.05 | U15: =(D15-C15)*24 -> 9.4333333 | Z15: =VLOOKUP(B15,Ref!$F$3:$H$367,3,FALSE) -> #N/A | AA15: =SUMIF(DailyAccomplishmentReport!$B$12:$B$43,B15,DailyAccomplishmentReport!$D$12:$D$43) -> 0 | AB15: =IF(F15=$F$9,2,IF(AND(E15>=0,F15<=$F$8),(F15-E15)*24,IF(F15>$E$9,(F15-$E$9)*24,0))) -> 0 | AC15: =ROUND(AB15*$AC$11,2) -> 0 | AD15: =ROUND((F15-E15)*24,2) -> 0 | AE15: =VLOOKUP(Z15,Ref!$C$3:$D$14,2,) -> #N/A | AF15: =AD15*AE15 -> #N/A
B16: =B15+1 -> 45966 | C16: 0.325 | D16: 0.72916667 | G16: =IF(AND(C16="",D16=""),"",IF(AND(C16<=$D$5,D16>=$E$5),8, IF(AND(Q16<4,Q16>0,R16>=0),8-S16,IF(AND(Q16<4,C16>$D$5,U16>5),T16-(S16+1), IF(AND(Q16>3,D16<$E$5),T16-S16,IF(AND(Q16>3,D16>=$E$5),9-S16,IF(AND(C16>$D$5,U16<=4),T16-S16,IF(AND(C16>$D$5,U16>4),U16-(S16+1),IF(AND(C16<=$D$5,U16>=5),T16-1,IF(AND(C16<=$D$5,T16<=4),T16,IF(AND(C16<=$D$5,T16<5),4,IF(U16>5,U16-1,IF(U16<=4,U16,0))))))))))))) -> 8 | H16: =IF(F16-E16*24=0,"",IF(ROUND((F16-E16)*24,2)>=6,ROUND((F16-E16)*24,2)-1,ROUND((F16-E16)*24,2))) | I16: Began coding the frontend components for the dashboard, setting up initial UI elements. | K16: =Billing!C41 -> 0 | L16: =Billing!D41 -> 0 | M16: ='Attendance Report - Manager'!G31 -> 8 | N16: ='Attendance Report - Manager'!H31 -> 0 | P16: =SUMIF(DailyAccomplishmentReport!$B$12:$B$26,B16,DailyAccomplishmentReport!$AP$12:$AP$26) -> 0 | Q16: =IF(C16<>"", (C16-$D$5)*24,0) -> -0.7 | R16: =IF(D16<>"", (D16-$E$5)*24,0) -> 0 | S16: =(ROUNDUP(Q16/0.5,0)*0.5 ) -> -1 | T16: =ROUND((D16-$D$5)*24,2) -> 9 | U16: =(D16-C16)*24 -> 9.7 | Z16: =VLOOKUP(B16,Ref!$F$3:$H$367,3,FALSE) -> #N/A | AA16: =SUMIF(DailyAccomplishmentReport!$B$12:$B$43,B16,DailyAccomplishmentReport!$D$12:$D$43) -> 0 | AB16: =IF(F16=$F$9,2,IF(AND(E16>=0,F16<=$F$8),(F16-E16)*24,IF(F16>$E$9,(F16-$E$9)*24,0))) -> 0 | AC16: =ROUND(AB16*$AC$11,2) -> 0 | AD16: =ROUND((F16-E16)*24,2) -> 0 | AE16: =VLOOKUP(Z16,Ref!$C$3:$D$14,2,) -> #N/A | AF16: =AD16*AE16 -> #N/A
B17: =B16+1 -> 45967 | C17: 0.33402778 | D17: 0.72916667 | G17: =IF(AND(C17="",D17=""),"",IF(AND(C17<=$D$5,D17>=$E$5),8, IF(AND(Q17<4,Q17>0,R17>=0),8-S17,IF(AND(Q17<4,C17>$D$5,U17>5),T17-(S17+1), IF(AND(Q17>3,D17<$E$5),T17-S17,IF(AND(Q17>3,D17>=$E$5),9-S17,IF(AND(C17>$D$5,U17<=4),T17-S17,IF(AND(C17>$D$5,U17>4),U17-(S17+1),IF(AND(C17<=$D$5,U17>=5),T17-1,IF(AND(C17<=$D$5,T17<=4),T17,IF(AND(C17<=$D$5,T17<5),4,IF(U17>5,U17-1,IF(U17<=4,U17,0))))))))))))) -> 8 | H17: =IF(F17-E17*24=0,"",IF(ROUND((F17-E17)*24,2)>=6,ROUND((F17-E17)*24,2)-1,ROUND((F17-E17)*24,2))) | I17: Worked on billers module frontend, connecting forms and validation logic. | K17: =Billing!C42 -> 0 | L17: =Billing!D42 -> 0 | M17: ='Attendance Report - Manager'!G32 -> 8 | N17: ='Attendance Report - Manager'!H32 -> 0 | P17: =SUMIF(DailyAccomplishmentReport!$B$12:$B$26,B17,DailyAccomplishmentReport!$AP$12:$AP$26) -> 0 | Q17: =IF(C17<>"", (C17-$D$5)*24,0) -> -0.48333333 | R17: =IF(D17<>"", (D17-$E$5)*24,0) -> 0 | S17: =(ROUNDUP(Q17/0.5,0)*0.5 ) -> -0.5 | T17: =ROUND((D17-$D$5)*24,2) -> 9 | U17: =(D17-C17)*24 -> 9.4833333 | Z17: =VLOOKUP(B17,Ref!$F$3:$H$367,3,FALSE) -> #N/A | AA17: =SUMIF(DailyAccomplishmentReport!$B$12:$B$43,B17,DailyAccomplishmentReport!$D$12:$D$43) -> 0 | AB17: =IF(F17=$F$9,2,IF(AND(E17>=0,F17<=$F$8),(F17-E17)*24,IF(F17>$E$9,(F17-$E$9)*24,0))) -> 0 | AC17: =ROUND(AB17*$AC$11,2) -> 0 | AD17: =ROUND((F17-E17)*24,2) -> 0 | AE17: =VLOOKUP(Z17,Ref!$C$3:$D$14,2,) -> #N/A | AF17: =AD17*AE17 -> #N/A
B18: =B17+1 -> 45968 | C18: 0.30069444 | D18: 0.73541667 | G18: =IF(AND(C18="",D18=""),"",IF(AND(C18<=$D$5,D18>=$E$5),8, IF(AND(Q18<4,Q18>0,R18>=0),8-S18,IF(AND(Q18<4,C18>$D$5,U18>5),T18-(S18+1), IF(AND(Q18>3,D18<$E$5),T18-S18,IF(AND(Q18>3,D18>=$E$5),9-S18,IF(AND(C18>$D$5,U18<=4),T18-S18,IF(AND(C18>$D$5,U18>4),U18-(S18+1),IF(AND(C18<=$D$5,U18>=5),T18-1,IF(AND(C18<=$D$5,T18<=4),T18,IF(AND(C18<=$D$5,T18<5),4,IF(U18>5,U18-1,IF(U18<=4,U18,0))))))))))))) -> 8 | H18: =IF(F18-E18*24=0,"",IF(ROUND((F18-E18)*24,2)>=6,ROUND((F18-E18)*24,2)-1,ROUND((F18-E18)*24,2))) | I18: Working on PDF CDeveloped frontend modules for the attendance feature, ensuring usability and accuracy.onverter reseach and implementation how to convert docx to pdf | K18: =Billing!C43 -> 0 | L18: =Billing!D43 -> 0 | M18: ='Attendance Report - Manager'!G33 -> 8 | N18: ='Attendance Report - Manager'!H33 -> 0 | P18: =SUMIF(DailyAccomplishmentReport!$B$12:$B$26,B18,DailyAccomplishmentReport!$AP$12:$AP$26) -> 0 | Q18: =IF(C18<>"", (C18-$D$5)*24,0) -> -1.2833333 | R18: =IF(D18<>"", (D18-$E$5)*24,0) -> 0.15 | S18: =(ROUNDUP(Q18/0.5,0)*0.5 ) -> -1.5 | T18: =ROUND((D18-$D$5)*24,2) -> 9.15 | U18: =(D18-C18)*24 -> 10.433333 | Z18: =VLOOKUP(B18,Ref!$F$3:$H$367,3,FALSE) -> #N/A | AA18: =SUMIF(DailyAccomplishmentReport!$B$12:$B$43,B18,DailyAccomplishmentReport!$D$12:$D$43) -> 0 | AB18: =IF(F18=$F$9,2,IF(AND(E18>=0,F18<=$F$8),(F18-E18)*24,IF(F18>$E$9,(F18-$E$9)*24,0))) -> 0 | AC18: =ROUND(AB18*$AC$11,2) -> 0 | AD18: =ROUND((F18-E18)*24,2) -> 0 | AE18: =VLOOKUP(Z18,Ref!$C$3:$D$14,2,) -> #N/A | AF18: =AD18*AE18 -> #N/A
B19: =B18+1 -> 45969 | G19: =IF(AND(C19="",D19=""),"",IF(AND(C19<=$D$5,D19>=$E$5),8, IF(AND(Q19<4,Q19>0,R19>=0),8-S19,IF(AND(Q19<4,C19>$D$5,U19>5),T19-(S19+1), IF(AND(Q19>3,D19<$E$5),T19-S19,IF(AND(Q19>3,D19>=$E$5),9-S19,IF(AND(C19>$D$5,U19<=4),T19-S19,IF(AND(C19>$D$5,U19>4),U19-(S19+1),IF(AND(C19<=$D$5,U19>=5),T19-1,IF(AND(C19<=$D$5,T19<=4),T19,IF(AND(C19<=$D$5,T19<5),4,IF(U19>5,U19-1,IF(U19<=4,U19,0))))))))))))) | K19: =Billing!C44 -> 0 | L19: =Billing!D44 -> 0 | M19: ='Attendance Report - Manager'!G34 -> 0 | N19: ='Attendance Report - Manager'!H34 -> 0 | P19: =SUMIF(DailyAccomplishmentReport!$B$12:$B$26,B19,DailyAccomplishmentReport!$AP$12:$AP$26) -> 0 | Q19: =IF(C19<>"", (C19-$D$5)*24,0) -> 0 | R19: =IF(D19<>"", (D19-$E$5)*24,0) -> 0 | S19: =(ROUNDUP(Q19/0.5,0)*0.5 ) -> 0 | T19: =ROUND((D19-$D$5)*24,2) -> -8.5 | U19: =(D19-C19)*24 -> 0 | Z19: =VLOOKUP(B19,Ref!$F$3:$H$367,3,FALSE) -> #N/A | AA19: =SUMIF(DailyAccomplishmentReport!$B$12:$B$43,B19,DailyAccomplishmentReport!$D$12:$D$43) -> 0 | AB19: =IF(F19=$F$9,2,IF(AND(E19>=0,F19<=$F$8),(F19-E19)*24,IF(F19>$E$9,(F19-$E$9)*24,0))) -> 0 | AC19: =ROUND(AB19*$AC$11,2) -> 0 | AD19: =ROUND((F19-E19)*24,2) -> 0 | AE19: =VLOOKUP(Z19,Ref!$C$3:$D$14,2,) -> #N/A | AF19: =AD19*AE19 -> #N/A
B20: =B19+1 -> 45970 | G20: =IF(AND(C20="",D20=""),"",IF(AND(C20<=$D$5,D20>=$E$5),8, IF(AND(Q20<4,Q20>0,R20>=0),8-S20,IF(AND(Q20<4,C20>$D$5,U20>5),T20-(S20+1), IF(AND(Q20>3,D20<$E$5),T20-S20,IF(AND(Q20>3,D20>=$E$5),9-S20,IF(AND(C20>$D$5,U20<=4),T20-S20,IF(AND(C20>$D$5,U20>4),U20-(S20+1),IF(AND(C20<=$D$5,U20>=5),T20-1,IF(AND(C20<=$D$5,T20<=4),T20,IF(AND(C20<=$D$5,T20<5),4,IF(U20>5,U20-1,IF(U20<=4,U20,0))))))))))))) | K20: =Billing!C45 -> 0 | L20: =Billing!D45 -> 0 | M20: ='Attendance Report - Manager'!G35 -> 0 | N20: ='Attendance Report - Manager'!H35 -> 0 | P20: =SUMIF(DailyAccomplishmentReport!$B$12:$B$26,B20,DailyAccomplishmentReport!$AP$12:$AP$26) -> 0 | Q20: =IF(C20<>"", (C20-$D$5)*24,0) -> 0 | R20: =IF(D20<>"", (D20-$E$5)*24,0) -> 0 | S20: =(ROUNDUP(Q20/0.5,0)*0.5 ) -> 0 | T20: =ROUND((D20-$D$5)*24,2) -> -8.5 | U20: =(D20-C20)*24 -> 0 | Z20: =VLOOKUP(B20,Ref!$F$3:$H$367,3,FALSE) -> #N/A | AA20: =SUMIF(DailyAccomplishmentReport!$B$12:$B$43,B20,DailyAccomplishmentReport!$D$12:$D$43) -> 0 | AB20: =IF(F20=$F$9,2,IF(AND(E20>=0,F20<=$F$8),(F20-E20)*24,IF(F20>$E$9,(F20-$E$9)*24,0))) -> 0 | AC20: =ROUND(AB20*$AC$11,2) -> 0 | AD20: =ROUND((F20-E20)*24,2) -> 0 | AE20: =VLOOKUP(Z20,Ref!$C$3:$D$14,2,) -> #N/A | AF20: =AD20*AE20 -> #N/A
B21: =B20+1 -> 45971 | G21: =IF(AND(C21="",D21=""),"",IF(AND(C21<=$D$5,D21>=$E$5),8, IF(AND(Q21<4,Q21>0,R21>=0),8-S21,IF(AND(Q21<4,C21>$D$5,U21>5),T21-(S21+1), IF(AND(Q21>3,D21<$E$5),T21-S21,IF(AND(Q21>3,D21>=$E$5),9-S21,IF(AND(C21>$D$5,U21<=4),T21-S21,IF(AND(C21>$D$5,U21>4),U21-(S21+1),IF(AND(C21<=$D$5,U21>=5),T21-1,IF(AND(C21<=$D$5,T21<=4),T21,IF(AND(C21<=$D$5,T21<5),4,IF(U21>5,U21-1,IF(U21<=4,U21,0))))))))))))) | K21: =Billing!C46 -> 0 | L21: =Billing!D46 -> 0 | M21: ='Attendance Report - Manager'!G36 -> 0 | N21: ='Attendance Report - Manager'!H36 -> 0 | P21: =SUMIF(DailyAccomplishmentReport!$B$12:$B$26,B21,DailyAccomplishmentReport!$AP$12:$AP$26) -> 0 | Q21: =IF(C21<>"", (C21-$D$5)*24,0) -> 0 | R21: =IF(D21<>"", (D21-$E$5)*24,0) -> 0 | S21: =(ROUNDUP(Q21/0.5,0)*0.5 ) -> 0 | T21: =ROUND((D21-$D$5)*24,2) -> -8.5 | U21: =(D21-C21)*24 -> 0 | Z21: =VLOOKUP(B21,Ref!$F$3:$H$367,3,FALSE) -> #N/A | AA21: =SUMIF(DailyAccomplishmentReport!$B$12:$B$43,B21,DailyAccomplishmentReport!$D$12:$D$43) -> 0 | AB21: =IF(F21=$F$9,2,IF(AND(E21>=0,F21<=$F$8),(F21-E21)*24,IF(F21>$E$9,(F21-$E$9)*24,0))) -> 0 | AC21: =ROUND(AB21*$AC$11,2) -> 0 | AD21: =ROUND((F21-E21)*24,2) -> 0 | AE21: =VLOOKUP(Z21,Ref!$C$3:$D$14,2,) -> #N/A | AF21: =AD21*AE21 -> #N/A
B22: =B21+1 -> 45972 | C22: 0.33263889 | D22: 0.72916667 | G22: =IF(AND(C22="",D22=""),"",IF(AND(C22<=$D$5,D22>=$E$5),8, IF(AND(Q22<4,Q22>0,R22>=0),8-S22,IF(AND(Q22<4,C22>$D$5,U22>5),T22-(S22+1), IF(AND(Q22>3,D22<$E$5),T22-S22,IF(AND(Q22>3,D22>=$E$5),9-S22,IF(AND(C22>$D$5,U22<=4),T22-S22,IF(AND(C22>$D$5,U22>4),U22-(S22+1),IF(AND(C22<=$D$5,U22>=5),T22-1,IF(AND(C22<=$D$5,T22<=4),T22,IF(AND(C22<=$D$5,T22<5),4,IF(U22>5,U22-1,IF(U22<=4,U22,0))))))))))))) -> 8 | H22: =IF(F22-E22*24=0,"",IF(ROUND((F22-E22)*24,2)>=6,ROUND((F22-E22)*24,2)-1,ROUND((F22-E22)*24,2))) | I22: Worked on billers module frontend, connecting forms and validation logic. | K22: =Billing!C47 -> 0 | L22: =Billing!D47 -> 0 | M22: ='Attendance Report - Manager'!G37 -> 8 | N22: ='Attendance Report - Manager'!H37 -> 0 | P22: =SUMIF(DailyAccomplishmentReport!$B$12:$B$26,B22,DailyAccomplishmentReport!$AP$12:$AP$26) -> 0 | Q22: =IF(C22<>"", (C22-$D$5)*24,0) -> -0.51666667 | R22: =IF(D22<>"", (D22-$E$5)*24,0) -> 0 | S22: =(ROUNDUP(Q22/0.5,0)*0.5 ) -> -1 | T22: =ROUND((D22-$D$5)*24,2) -> 9 | U22: =(D22-C22)*24 -> 9.5166667 | Z22: =VLOOKUP(B22,Ref!$F$3:$H$367,3,FALSE) -> #N/A | AA22: =SUMIF(DailyAccomplishmentReport!$B$12:$B$43,B22,DailyAccomplishmentReport!$D$12:$D$43) -> 0 | AB22: =IF(F22=$F$9,2,IF(AND(E22>=0,F22<=$F$8),(F22-E22)*24,IF(F22>$E$9,(F22-$E$9)*24,0))) -> 0 | AC22: =ROUND(AB22*$AC$11,2) -> 0 | AD22: =ROUND((F22-E22)*24,2) -> 0 | AE22: =VLOOKUP(Z22,Ref!$C$3:$D$14,2,) -> #N/A | AF22: =AD22*AE22 -> #N/A
B23: =B22+1 -> 45973 | C23: 0.325 | D23: 0.63888889 | G23: =IF(AND(C23="",D23=""),"",IF(AND(C23<=$D$5,D23>=$E$5),8, IF(AND(Q23<4,Q23>0,R23>=0),8-S23,IF(AND(Q23<4,C23>$D$5,U23>5),T23-(S23+1), IF(AND(Q23>3,D23<$E$5),T23-S23,IF(AND(Q23>3,D23>=$E$5),9-S23,IF(AND(C23>$D$5,U23<=4),T23-S23,IF(AND(C23>$D$5,U23>4),U23-(S23+1),IF(AND(C23<=$D$5,U23>=5),T23-1,IF(AND(C23<=$D$5,T23<=4),T23,IF(AND(C23<=$D$5,T23<5),4,IF(U23>5,U23-1,IF(U23<=4,U23,0))))))))))))) -> 5.83 | H23: =IF(F23-E23*24=0,"",IF(ROUND((F23-E23)*24,2)>=6,ROUND((F23-E23)*24,2)-1,ROUND((F23-E23)*24,2))) | I23: Adjusted and fixed backend issues | K23: =Billing!C48 -> 0 | L23: =Billing!D48 -> 0 | M23: ='Attendance Report - Manager'!G38 -> 6.53 | N23: ='Attendance Report - Manager'!H38 -> 0 | P23: =SUMIF(DailyAccomplishmentReport!$B$12:$B$26,B23,DailyAccomplishmentReport!$AP$12:$AP$26) -> 0 | Q23: =IF(C23<>"", (C23-$D$5)*24,0) -> -0.7 | R23: =IF(D23<>"", (D23-$E$5)*24,0) -> -2.1666667 | S23: =(ROUNDUP(Q23/0.5,0)*0.5 ) -> -1 | T23: =ROUND((D23-$D$5)*24,2) -> 6.83 | U23: =(D23-C23)*24 -> 7.5333333 | Z23: =VLOOKUP(B23,Ref!$F$3:$H$367,3,FALSE) -> #N/A | AA23: =SUMIF(DailyAccomplishmentReport!$B$12:$B$43,B23,DailyAccomplishmentReport!$D$12:$D$43) -> 0 | AB23: =IF(F23=$F$9,2,IF(AND(E23>=0,F23<=$F$8),(F23-E23)*24,IF(F23>$E$9,(F23-$E$9)*24,0))) -> 0 | AC23: =ROUND(AB23*$AC$11,2) -> 0 | AD23: =ROUND((F23-E23)*24,2) -> 0 | AE23: =VLOOKUP(Z23,Ref!$C$3:$D$14,2,) -> #N/A | AF23: =AD23*AE23 -> #N/A
B24: =B23+1 -> 45974 | C24: 0.33472222 | D24: 0.72916667 | G24: =IF(AND(C24="",D24=""),"",IF(AND(C24<=$D$5,D24>=$E$5),8, IF(AND(Q24<4,Q24>0,R24>=0),8-S24,IF(AND(Q24<4,C24>$D$5,U24>5),T24-(S24+1), IF(AND(Q24>3,D24<$E$5),T24-S24,IF(AND(Q24>3,D24>=$E$5),9-S24,IF(AND(C24>$D$5,U24<=4),T24-S24,IF(AND(C24>$D$5,U24>4),U24-(S24+1),IF(AND(C24<=$D$5,U24>=5),T24-1,IF(AND(C24<=$D$5,T24<=4),T24,IF(AND(C24<=$D$5,T24<5),4,IF(U24>5,U24-1,IF(U24<=4,U24,0))))))))))))) -> 8 | H24: =IF(F24-E24*24=0,"",IF(ROUND((F24-E24)*24,2)>=6,ROUND((F24-E24)*24,2)-1,ROUND((F24-E24)*24,2))) | I24: Finalized backend adjustments | K24: =Billing!C49 -> 0 | L24: =Billing!D49 -> 0 | M24: ='Attendance Report - Manager'!G39 -> 8 | N24: ='Attendance Report - Manager'!H39 -> 0 | P24: =SUMIF(DailyAccomplishmentReport!$B$12:$B$26,B24,DailyAccomplishmentReport!$AP$12:$AP$26) -> 0 | Q24: =IF(C24<>"", (C24-$D$5)*24,0) -> -0.46666667 | R24: =IF(D24<>"", (D24-$E$5)*24,0) -> 0 | S24: =(ROUNDUP(Q24/0.5,0)*0.5 ) -> -0.5 | T24: =ROUND((D24-$D$5)*24,2) -> 9 | U24: =(D24-C24)*24 -> 9.4666667 | Z24: =VLOOKUP(B24,Ref!$F$3:$H$367,3,FALSE) -> #N/A | AA24: =SUMIF(DailyAccomplishmentReport!$B$12:$B$43,B24,DailyAccomplishmentReport!$D$12:$D$43) -> 0 | AB24: =IF(F24=$F$9,2,IF(AND(E24>=0,F24<=$F$8),(F24-E24)*24,IF(F24>$E$9,(F24-$E$9)*24,0))) -> 0 | AC24: =ROUND(AB24*$AC$11,2) -> 0 | AD24: =ROUND((F24-E24)*24,2) -> 0 | AE24: =VLOOKUP(Z24,Ref!$C$3:$D$14,2,) -> #N/A | AF24: =AD24*AE24 -> #N/A
B25: =B24+1 -> 45975 | C25: 0.29305556 | D25: 0.72916667 | G25: =IF(AND(C25="",D25=""),"",IF(AND(C25<=$D$5,D25>=$E$5),8, IF(AND(Q25<4,Q25>0,R25>=0),8-S25,IF(AND(Q25<4,C25>$D$5,U25>5),T25-(S25+1), IF(AND(Q25>3,D25<$E$5),T25-S25,IF(AND(Q25>3,D25>=$E$5),9-S25,IF(AND(C25>$D$5,U25<=4),T25-S25,IF(AND(C25>$D$5,U25>4),U25-(S25+1),IF(AND(C25<=$D$5,U25>=5),T25-1,IF(AND(C25<=$D$5,T25<=4),T25,IF(AND(C25<=$D$5,T25<5),4,IF(U25>5,U25-1,IF(U25<=4,U25,0))))))))))))) -> 8 | H25: =IF(F25-E25*24=0,"",IF(ROUND((F25-E25)*24,2)>=6,ROUND((F25-E25)*24,2)-1,ROUND((F25-E25)*24,2))) | I25: Conducted thorough debugging across modules | K25: =Billing!C50 -> 0 | L25: =Billing!D50 -> 0 | M25: ='Attendance Report - Manager'!G40 -> 8 | N25: ='Attendance Report - Manager'!H40 -> 0 | P25: =SUMIF(DailyAccomplishmentReport!$B$12:$B$26,B25,DailyAccomplishmentReport!$AP$12:$AP$26) -> 0 | Q25: =IF(C25<>"", (C25-$D$5)*24,0) -> -1.4666667 | R25: =IF(D25<>"", (D25-$E$5)*24,0) -> 0 | S25: =(ROUNDUP(Q25/0.5,0)*0.5 ) -> -1.5 | T25: =ROUND((D25-$D$5)*24,2) -> 9 | U25: =(D25-C25)*24 -> 10.466667 | Z25: =VLOOKUP(B25,Ref!$F$3:$H$367,3,FALSE) -> #N/A | AA25: =SUMIF(DailyAccomplishmentReport!$B$12:$B$43,B25,DailyAccomplishmentReport!$D$12:$D$43) -> 0 | AB25: =IF(F25=$F$9,2,IF(AND(E25>=0,F25<=$F$8),(F25-E25)*24,IF(F25>$E$9,(F25-$E$9)*24,0))) -> 0 | AC25: =ROUND(AB25*$AC$11,2) -> 0 | AD25: =ROUND((F25-E25)*24,2) -> 0 | AE25: =VLOOKUP(Z25,Ref!$C$3:$D$14,2,) -> #N/A | AF25: =AD25*AE25 -> #N/A
B26: =B25+1 -> 45976 | G26: =IF(AND(C26="",D26=""),"",IF(AND(C26<=$D$5,D26>=$E$5),8, IF(AND(Q26<4,Q26>0,R26>=0),8-S26,IF(AND(Q26<4,C26>$D$5,U26>5),T26-(S26+1), IF(AND(Q26>3,D26<$E$5),T26-S26,IF(AND(Q26>3,D26>=$E$5),9-S26,IF(AND(C26>$D$5,U26<=4),T26-S26,IF(AND(C26>$D$5,U26>4),U26-(S26+1),IF(AND(C26<=$D$5,U26>=5),T26-1,IF(AND(C26<=$D$5,T26<=4),T26,IF(AND(C26<=$D$5,T26<5),4,IF(U26>5,U26-1,IF(U26<=4,U26,0))))))))))))) | H26: =IF(F26-E26*24=0,"",IF(ROUND((F26-E26)*24,2)>=6,ROUND((F26-E26)*24,2)-1,ROUND((F26-E26)*24,2))) | K26: =Billing!C51 -> 0 | L26: =Billing!D51 -> 0 | M26: ='Attendance Report - Manager'!G41 -> 0 | N26: ='Attendance Report - Manager'!H41 -> 0 | P26: =SUMIF(DailyAccomplishmentReport!$B$12:$B$26,B26,DailyAccomplishmentReport!$AP$12:$AP$26) -> 0 | Q26: =IF(C26<>"", (C26-$D$5)*24,0) -> 0 | R26: =IF(D26<>"", (D26-$E$5)*24,0) -> 0 | S26: =(ROUNDUP(Q26/0.5,0)*0.5 ) -> 0 | T26: =ROUND((D26-$D$5)*24,2) -> -8.5 | U26: =(D26-C26)*24 -> 0 | Z26: =VLOOKUP(B26,Ref!$F$3:$H$367,3,FALSE) -> #N/A | AA26: =SUMIF(DailyAccomplishmentReport!$B$12:$B$43,B26,DailyAccomplishmentReport!$D$12:$D$43) -> 0 | AB26: =IF(F26=$F$9,2,IF(AND(E26>=0,F26<=$F$8),(F26-E26)*24,IF(F26>$E$9,(F26-$E$9)*24,0))) -> 0 | AC26: =ROUND(AB26*$AC$11,2) -> 0 | AD26: =ROUND((F26-E26)*24,2) -> 0 | AE26: =VLOOKUP(Z26,Ref!$C$3:$D$14,2,) -> #N/A | AF26: =AD26*AE26 -> #N/A
G27: =IF(AND(C27="",D27=""),"",IF(AND(C27<=$D$5,D27>=$E$5),8, IF(AND(Q28<4,Q28>0,R28>=0),8-S28,IF(AND(Q28<4,C27>$D$5,U28>5),T28-(S28+1), IF(AND(Q28>3,D27<$E$5),T28-S28,IF(AND(Q28>3,D27>=$E$5),9-S28,IF(AND(C27>$D$5,U28<=4),T28-S28,IF(AND(C27>$D$5,U28>4),U28-(S28+1),IF(AND(C27<=$D$5,U28>=5),T28-1,IF(AND(C27<=$D$5,T28<=4),T28,IF(AND(C27<=$D$5,T28<5),4,IF(U28>5,U28-1,IF(U28<=4,U28,0))))))))))))) | K27: =Billing!C52 -> 0 | L27: =Billing!D52 -> 0 | M27: ='Attendance Report - Manager'!G42 -> #REF! | N27: ='Attendance Report - Manager'!H42 -> #REF! | P27: =SUMIF(DailyAccomplishmentReport!$B$12:$B$26,#REF!,DailyAccomplishmentReport!$AP$12:$AP$26) -> 0 | Q27: =IF(#REF!<>"", (#REF!-$D$5)*24,0) -> #REF! | R27: =IF(#REF!<>"", (#REF!-$E$5)*24,0) -> #REF! | S27: =(ROUNDUP(Q27/0.5,0)*0.5 ) -> #REF! | T27: =ROUND((#REF!-$D$5)*24,2) -> #REF! | U27: =(#REF!-#REF!)*24 -> #REF! | Z27: =VLOOKUP(#REF!,Ref!$F$3:$H$367,3,FALSE) -> #REF! | AA27: =SUMIF(DailyAccomplishmentReport!$B$12:$B$43,#REF!,DailyAccomplishmentReport!$D$12:$D$43) -> 0 | AB27: =IF(#REF!=$F$9,2,IF(AND(#REF!>=0,#REF!<=$F$8),(#REF!-#REF!)*24,IF(#REF!>$E$9,(#REF!-$E$9)*24,0))) -> #REF! | AC27: =ROUND(AB27*$AC$11,2) -> #REF! | AD27: =ROUND((#REF!-#REF!)*24,2) -> #REF! | AE27: =VLOOKUP(Z27,Ref!$C$3:$D$14,2,) -> #REF! | AF27: =AD27*AE27 -> #REF!
C28: Total | G28: =SUM(G12:G27) -> 69.83 | H28: =SUM(H12:H27) -> 0
B30: Certified Correct: | H30: Reviewed: Approved:
B32: MIKAELLA ANDREA DEVELOS | H32: ='Attendance Report_Second'!H32:I32 -> JUN M. SALVANERA | J32: ='Attendance Report_Second'!J32 -> HELEN D. PACIENCIA
B33: --------------------------------------------------------- | H33: ------------------------------------------- -----------------------------------------------
B34: Employee Signature over Printed Name | H34: Reviewed By Approved By
H35: (Signature over Printed Name) (Signature over Printed Name)

Sheet Attendance Report_Second
B1: RADIX
B4: Name | D4: MIKAELLA ANDREA DEVELOS
B5: Shift Schedule | D5: 0.35416667 | E5: 0.72916667 | F5: 0.00069444444 | G5: =E5-F5 -> 0.72847222
B6: Client | D6: Maybank Phil. Inc.
B7: Payroll Period | D7: From | E7: To
D8: 45977 | E8: 11/30/35 | F8: 0.25
E9: 0.91666667 | F9: 1
B10: Date | C10: Regular Hrs | E10: Overtime | G10: Total Hrs | I10: Remarks
C11: In | D11: Out | E11: In | F11: Out | G11: Regular | H11: OT | AB11: Night Diff | AC11: 0.1 | AD11: OTs | AE11: Int(%) | AF11: OT Total
B12: =D8 -> 45977 | H12: =IF(F12-E12*24=0,"",IF(ROUND((F12-E12)*24,2)>=6,ROUND((F12-E12)*24,2)-1,ROUND((F12-E12)*24,2))) | K12: =Billing!C22 -> 0 | L12: =Billing!D22 -> 0 | M12: ='Attendance Report - Manager'!G12 -> 0 | N12: ='Attendance Report - Manager'!H12 -> 0 | P12: =SUMIF(DailyAccomplishmentReport!$B$12:$B$26,B12,DailyAccomplishmentReport!$AP$12:$AP$26) -> 0 | Q12: =IF(C12<>"", (C12-$D$5)*24,0) -> 0 | R12: =IF(D12<>"", (D12-$E$5)*24,0) -> 0 | S12: =(ROUNDUP(Q12/0.5,0)*0.5 ) -> 0 | T12: =ROUND((D12-$D$5)*24,2) -> -8.5 | U12: =(D12-C12)*24 -> 0 | Z12: =VLOOKUP(B12,Ref!$F$3:$H$367,3,FALSE) -> #N/A | AA12: =SUMIF(DailyAccomplishmentReport!$B$12:$B$43,B12,DailyAccomplishmentReport!$D$12:$D$43) -> 0 | AB12: =IF(F12=$F$9,2,IF(AND(E12>=0,F12<=$F$8),(F12-E12)*24,IF(F12>$E$9,(F12-$E$9)*24,0))) -> 0 | AC12: =ROUND(AB12*$AC$11,2) -> 0 | AD12: =ROUND((F12-E12)*24,2) -> 0 | AE12: =VLOOKUP(Z12,Ref!$C$3:$D$14,2,) -> #N/A | AF12: =AD12*AE12 -> #N/A
B13: =B12+1 -> 45978 | C13: 0.35416667 | D13: 0.76805556 | G13: =IF(AND(C13="",D13=""),"",IF(AND(C13<=$D$5,D13>=$E$5),8, IF(AND(Q13<4,Q13>0,R13>=0),8-S13,IF(AND(Q13<4,C13>$D$5,U13>5),T13-(S13+1), IF(AND(Q13>3,D13<$E$5),T13-S13,IF(AND(Q13>3,D13>=$E$5),9-S13,IF(AND(C13>$D$5,U13<=4),T13-S13,IF(AND(C13>$D$5,U13>4),U13-(S13+1),IF(AND(C13<=$D$5,U13>=5),T13-1,IF(AND(C13<=$D$5,T13<=4),T13,IF(AND(C13<=$D$5,T13<5),4,IF(U13>5,U13-1,IF(U13<=4,U13,0))))))))))))) -> 8 | H13: =IF(F13-E13*24=0,"",IF(ROUND((F13-E13)*24,2)>=6,ROUND((F13-E13)*24,2)-1,ROUND((F13-E13)*24,2))) | I13: Worked on billers module frontend, connecting forms and validation logic. | K13: =Billing!C23 -> 0 | L13: =Billing!D23 -> 0 | M13: ='Attendance Report - Manager'!G13 -> 8 | N13: ='Attendance Report - Manager'!H13 -> 0 | P13: =SUMIF(DailyAccomplishmentReport!$B$12:$B$26,B13,DailyAccomplishmentReport!$AP$12:$AP$26) -> 0 | Q13: =IF(C13<>"", (C13-$D$5)*24,0) -> 0 | R13: =IF(D13<>"", (D13-$E$5)*24,0) -> 0.93333333 | S13: =(ROUNDUP(Q13/0.5,0)*0.5 ) -> 0 | T13: =ROUND((D13-$D$5)*24,2) -> 9.93 | U13: =(D13-C13)*24 -> 9.9333333 | Z13: =VLOOKUP(B13,Ref!$F$3:$H$367,3,FALSE) -> #N/A | AA13: =SUMIF(DailyAccomplishmentReport!$B$12:$B$43,B13,DailyAccomplishmentReport!$D$12:$D$43) -> 0 | AB13: =IF(F13=$F$9,2,IF(AND(E13>=0,F13<=$F$8),(F13-E13)*24,IF(F13>$E$9,(F13-$E$9)*24,0))) -> 0 | AC13: =ROUND(AB13*$AC$11,2) -> 0 | AD13: =ROUND((F13-E13)*24,2) -> 0 | AE13: =VLOOKUP(Z13,Ref!$C$3:$D$14,2,) -> #N/A | AF13: =AD13*AE13 -> #N/A
B14: =B13+1 -> 45979 | C14: 0.34236111 | D14: 0.77361111 | G14: =IF(AND(C14="",D14=""),"",IF(AND(C14<=$D$5,D14>=$E$5),8, IF(AND(Q14<4,Q14>0,R14>=0),8-S14,IF(AND(Q14<4,C14>$D$5,U14>5),T14-(S14+1), IF(AND(Q14>3,D14<$E$5),T14-S14,IF(AND(Q14>3,D14>=$E$5),9-S14,IF(AND(C14>$D$5,U14<=4),T14-S14,IF(AND(C14>$D$5,U14>4),U14-(S14+1),IF(AND(C14<=$D$5,U14>=5),T14-1,IF(AND(C14<=$D$5,T14<=4),T14,IF(AND(C14<=$D$5,T14<5),4,IF(U14>5,U14-1,IF(U14<=4,U14,0))))))))))))) -> 8 | H14: =IF(F14-E14*24=0,"",IF(ROUND((F14-E14)*24,2)>=6,ROUND((F14-E14)*24,2)-1,ROUND((F14-E14)*24,2))) | I14: Worked on billers module frontend, connecting forms and validation logic. | K14: =Billing!C24 -> 0 | L14: =Billing!D24 -> 0 | M14: ='Attendance Report - Manager'!G14 -> 8 | N14: ='Attendance Report - Manager'!H14 -> 0 | P14: =SUMIF(DailyAccomplishmentReport!$B$12:$B$26,B14,DailyAccomplishmentReport!$AP$12:$AP$26) -> 0 | Q14: =IF(C14<>"", (C14-$D$5)*24,0) -> -0.28333333 | R14: =IF(D14<>"", (D14-$E$5)*24,0) -> 1.0666667 | S14: =(ROUNDUP(Q14/0.5,0)*0.5 ) -> -0.5 | T14: =ROUND((D14-$D$5)*24,2) -> 10.07 | U14: =(D14-C14)*24 -> 10.35 | Z14: =VLOOKUP(B14,Ref!$F$3:$H$367,3,FALSE) -> #N/A | AA14: =SUMIF(DailyAccomplishmentReport!$B$12:$B$43,B14,DailyAccomplishmentReport!$D$12:$D$43) -> 0 | AB14: =IF(F14=$F$9,2,IF(AND(E14>=0,F14<=$F$8),(F14-E14)*24,IF(F14>$E$9,(F14-$E$9)*24,0))) -> 0 | AC14: =ROUND(AB14*$AC$11,2) -> 0 | AD14: =ROUND((F14-E14)*24,2) -> 0 | AE14: =VLOOKUP(Z14,Ref!$C$3:$D$14,2,) -> #N/A | AF14: =AD14*AE14 -> #N/A
B15: =B14+1 -> 45980 | C15: 0.32708333 | D15: 0.7625 | G15: =IF(AND(C15="",D15=""),"",IF(AND(C15<=$D$5,D15>=$E$5),8, IF(AND(Q15<4,Q15>0,R15>=0),8-S15,IF(AND(Q15<4,C15>$D$5,U15>5),T15-(S15+1), IF(AND(Q15>3,D15<$E$5),T15-S15,IF(AND(Q15>3,D15>=$E$5),9-S15,IF(AND(C15>$D$5,U15<=4),T15-S15,IF(AND(C15>$D$5,U15>4),U15-(S15+1),IF(AND(C15<=$D$5,U15>=5),T15-1,IF(AND(C15<=$D$5,T15<=4),T15,IF(AND(C15<=$D$5,T15<5),4,IF(U15>5,U15-1,IF(U15<=4,U15,0))))))))))))) -> 8 | H15: =IF(F15-E15*24=0,"",IF(ROUND((F15-E15)*24,2)>=6,ROUND((F15-E15)*24,2)-1,ROUND((F15-E15)*24,2))) | I15: Worked on billers module frontend, connecting forms and validation logic. | K15: =Billing!C25 -> 0 | L15: =Billing!D25 -> 0 | M15: ='Attendance Report - Manager'!G15 -> 8 | N15: ='Attendance Report - Manager'!H15 -> 0 | P15: =SUMIF(DailyAccomplishmentReport!$B$12:$B$26,B15,DailyAccomplishmentReport!$AP$12:$AP$26) -> 0 | Q15: =IF(C15<>"", (C15-$D$5)*24,0) -> -0.65 | R15: =IF(D15<>"", (D15-$E$5)*24,0) -> 0.8 | S15: =(ROUNDUP(Q15/0.5,0)*0.5 ) -> -1 | T15: =ROUND((D15-$D$5)*24,2) -> 9.8 | U15: =(D15-C15)*24 -> 10.45 | Z15: =VLOOKUP(B15,Ref!$F$3:$H$367,3,FALSE) -> #N/A | AA15: =SUMIF(DailyAccomplishmentReport!$B$12:$B$43,B15,DailyAccomplishmentReport!$D$12:$D$43) -> 0 | AB15: =IF(F15=$F$9,2,IF(AND(E15>=0,F15<=$F$8),(F15-E15)*24,IF(F15>$E$9,(F15-$E$9)*24,0))) -> 0 | AC15: =ROUND(AB15*$AC$11,2) -> 0 | AD15: =ROUND((F15-E15)*24,2) -> 0 | AE15: =VLOOKUP(Z15,Ref!$C$3:$D$14,2,) -> #N/A | AF15: =AD15*AE15 -> #N/A
B16: =B15+1 -> 45981 | C16: 0.35416667 | D16: 0.79375 | G16: =IF(AND(C16="",D16=""),"",IF(AND(C16<=$D$5,D16>=$E$5),8, IF(AND(Q16<4,Q16>0,R16>=0),8-S16,IF(AND(Q16<4,C16>$D$5,U16>5),T16-(S16+1), IF(AND(Q16>3,D16<$E$5),T16-S16,IF(AND(Q16>3,D16>=$E$5),9-S16,IF(AND(C16>$D$5,U16<=4),T16-S16,IF(AND(C16>$D$5,U16>4),U16-(S16+1),IF(AND(C16<=$D$5,U16>=5),T16-1,IF(AND(C16<=$D$5,T16<=4),T16,IF(AND(C16<=$D$5,T16<5),4,IF(U16>5,U16-1,IF(U16<=4,U16,0))))))))))))) -> 8 | H16: =IF(F16-E16*24=0,"",IF(ROUND((F16-E16)*24,2)>=6,ROUND((F16-E16)*24,2)-1,ROUND((F16-E16)*24,2))) | I16: Assisted instapay testing | K16: =Billing!C26 -> 0 | L16: =Billing!D26 -> 0 | M16: ='Attendance Report - Manager'!G16 -> 8 | N16: ='Attendance Report - Manager'!H16 -> 0 | P16: =SUMIF(DailyAccomplishmentReport!$B$12:$B$26,B16,DailyAccomplishmentReport!$AP$12:$AP$26) -> 0 | Q16: =IF(C16<>"", (C16-$D$5)*24,0) -> 0 | R16: =IF(D16<>"", (D16-$E$5)*24,0) -> 1.55 | S16: =(ROUNDUP(Q16/0.5,0)*0.5 ) -> 0 | T16: =ROUND((D16-$D$5)*24,2) -> 10.55 | U16: =(D16-C16)*24 -> 10.55 | Z16: =VLOOKUP(B16,Ref!$F$3:$H$367,3,FALSE) -> #N/A | AA16: =SUMIF(DailyAccomplishmentReport!$B$12:$B$43,B16,DailyAccomplishmentReport!$D$12:$D$43) -> 0 | AB16: =IF(F16=$F$9,2,IF(AND(E16>=0,F16<=$F$8),(F16-E16)*24,IF(F16>$E$9,(F16-$E$9)*24,0))) -> 0 | AC16: =ROUND(AB16*$AC$11,2) -> 0 | AD16: =ROUND((F16-E16)*24,2) -> 0 | AE16: =VLOOKUP(Z16,Ref!$C$3:$D$14,2,) -> #N/A | AF16: =AD16*AE16 -> #N/A
B17: =B16+1 -> 45982 | C17: 0.32083333 | D17: 0.74513889 | G17: =IF(AND(C17="",D17=""),"",IF(AND(C17<=$D$5,D17>=$E$5),8, IF(AND(Q17<4,Q17>0,R17>=0),8-S17,IF(AND(Q17<4,C17>$D$5,U17>5),T17-(S17+1), IF(AND(Q17>3,D17<$E$5),T17-S17,IF(AND(Q17>3,D17>=$E$5),9-S17,IF(AND(C17>$D$5,U17<=4),T17-S17,IF(AND(C17>$D$5,U17>4),U17-(S17+1),IF(AND(C17<=$D$5,U17>=5),T17-1,IF(AND(C17<=$D$5,T17<=4),T17,IF(AND(C17<=$D$5,T17<5),4,IF(U17>5,U17-1,IF(U17<=4,U17,0))))))))))))) -> 8 | H17: =IF(F17-E17*24=0,"",IF(ROUND((F17-E17)*24,2)>=6,ROUND((F17-E17)*24,2)-1,ROUND((F17-E17)*24,2))) | I17: Assisted instapay testing | K17: =Billing!C27 -> 0 | L17: =Billing!D27 -> 0 | M17: ='Attendance Report - Manager'!G17 -> 8 | N17: ='Attendance Report - Manager'!H17 -> 0 | P17: =SUMIF(DailyAccomplishmentReport!$B$12:$B$26,B17,DailyAccomplishmentReport!$AP$12:$AP$26) -> 0 | Q17: =IF(C17<>"", (C17-$D$5)*24,0) -> -0.8 | R17: =IF(D17<>"", (D17-$E$5)*24,0) -> 0.38333333 | S17: =(ROUNDUP(Q17/0.5,0)*0.5 ) -> -1 | T17: =ROUND((D17-$D$5)*24,2) -> 9.38 | U17: =(D17-C17)*24 -> 10.183333 | Z17: =VLOOKUP(B17,Ref!$F$3:$H$367,3,FALSE) -> #N/A | AA17: =SUMIF(DailyAccomplishmentReport!$B$12:$B$43,B17,DailyAccomplishmentReport!$D$12:$D$43) -> 0 | AB17: =IF(F17=$F$9,2,IF(AND(E17>=0,F17<=$F$8),(F17-E17)*24,IF(F17>$E$9,(F17-$E$9)*24,0))) -> 0 | AC17: =ROUND(AB17*$AC$11,2) -> 0 | AD17: =ROUND((F17-E17)*24,2) -> 0 | AE17: =VLOOKUP(Z17,Ref!$C$3:$D$14,2,) -> #N/A | AF17: =AD17*AE17 -> #N/A
B18: =B17+1 -> 45983 | G18: =IF(AND(C18="",D18=""),"",IF(AND(C18<=$D$5,D18>=$E$5),8, IF(AND(Q18<4,Q18>0,R18>=0),8-S18,IF(AND(Q18<4,C18>$D$5,U18>5),T18-(S18+1), IF(AND(Q18>3,D18<$E$5),T18-S18,IF(AND(Q18>3,D18>=$E$5),9-S18,IF(AND(C18>$D$5,U18<=4),T18-S18,IF(AND(C18>$D$5,U18>4),U18-(S18+1),IF(AND(C18<=$D$5,U18>=5),T18-1,IF(AND(C18<=$D$5,T18<=4),T18,IF(AND(C18<=$D$5,T18<5),4,IF(U18>5,U18-1,IF(U18<=4,U18,0))))))))))))) | H18: =IF(F18-E18*24=0,"",IF(ROUND((F18-E18)*24,2)>=6,ROUND((F18-E18)*24,2)-1,ROUND((F18-E18)*24,2))) | K18: =Billing!C28 -> 0 | L18: =Billing!D28 -> 0 | M18: ='Attendance Report - Manager'!G18 -> 0 | N18: ='Attendance Report - Manager'!H18 -> 0 | P18: =SUMIF(DailyAccomplishmentReport!$B$12:$B$26,B18,DailyAccomplishmentReport!$AP$12:$AP$26) -> 0 | Q18: =IF(C18<>"", (C18-$D$5)*24,0) -> 0 | R18: =IF(D18<>"", (D18-$E$5)*24,0) -> 0 | S18: =(ROUNDUP(Q18/0.5,0)*0.5 ) -> 0 | T18: =ROUND((D18-$D$5)*24,2) -> -8.5 | U18: =(D18-C18)*24 -> 0 | Z18: =VLOOKUP(B18,Ref!$F$3:$H$367,3,FALSE) -> #N/A | AA18: =SUMIF(DailyAccomplishmentReport!$B$12:$B$43,B18,DailyAccomplishmentReport!$D$12:$D$43) -> 0 | AB18: =IF(F18=$F$9,2,IF(AND(E18>=0,F18<=$F$8),(F18-E18)*24,IF(F18>$E$9,(F18-$E$9)*24,0))) -> 0 | AC18: =ROUND(AB18*$AC$11,2) -> 0 | AD18: =ROUND((F18-E18)*24,2) -> 0 | AE18: =VLOOKUP(Z18,Ref!$C$3:$D$14,2,) -> #N/A | AF18: =AD18*AE18 -> #N/A
B19: =B18+1 -> 45984 | H19: =IF(F19-E19*24=0,"",IF(ROUND((F19-E19)*24,2)>=6,ROUND((F19-E19)*24,2)-1,ROUND((F19-E19)*24,2))) | K19: =Billing!C29 -> 0 | L19: =Billing!D29 -> 0 | M19: ='Attendance Report - Manager'!G19 -> 0 | N19: ='Attendance Report - Manager'!H19 -> 0 | P19: =SUMIF(DailyAccomplishmentReport!$B$12:$B$26,B19,DailyAccomplishmentReport!$AP$12:$AP$26) -> 0 | Q19: =IF(C19<>"", (C19-$D$5)*24,0) -> 0 | R19: =IF(D19<>"", (D19-$E$5)*24,0) -> 0 | S19: =(ROUNDUP(Q19/0.5,0)*0.5 ) -> 0 | T19: =ROUND((D19-$D$5)*24,2) -> -8.5 | U19: =(D19-C19)*24 -> 0 | Z19: =VLOOKUP(B19,Ref!$F$3:$H$367,3,FALSE) -> #N/A | AA19: =SUMIF(DailyAccomplishmentReport!$B$12:$B$43,B19,DailyAccomplishmentReport!$D$12:$D$43) -> 0 | AB19: =IF(F19=$F$9,2,IF(AND(E19>=0,F19<=$F$8),(F19-E19)*24,IF(F19>$E$9,(F19-$E$9)*24,0))) -> 0 | AC19: =ROUND(AB19*$AC$11,2) -> 0 | AD19: =ROUND((F19-E19)*24,2) -> 0 | AE19: =VLOOKUP(Z19,Ref!$C$3:$D$14,2,) -> #N/A | AF19: =AD19*AE19 -> #N/A
B20: =B19+1 -> 45985 | C20: 0.34583333 | D20: 0.73194444 | G20: =IF(AND(C20="",D20=""),"",IF(AND(C20<=$D$5,D20>=$E$5),8, IF(AND(Q20<4,Q20>0,R20>=0),8-S20,IF(AND(Q20<4,C20>$D$5,U20>5),T20-(S20+1), IF(AND(Q20>3,D20<$E$5),T20-S20,IF(AND(Q20>3,D20>=$E$5),9-S20,IF(AND(C20>$D$5,U20<=4),T20-S20,IF(AND(C20>$D$5,U20>4),U20-(S20+1),IF(AND(C20<=$D$5,U20>=5),T20-1,IF(AND(C20<=$D$5,T20<=4),T20,IF(AND(C20<=$D$5,T20<5),4,IF(U20>5,U20-1,IF(U20<=4,U20,0))))))))))))) -> 8 | H20: =IF(F20-E20*24=0,"",IF(ROUND((F20-E20)*24,2)>=6,ROUND((F20-E20)*24,2)-1,ROUND((F20-E20)*24,2))) | I20: Worked on instapay dashboard | K20: =Billing!C30 -> 0 | L20: =Billing!D30 -> 0 | M20: ='Attendance Report - Manager'!G20 -> 8 | N20: ='Attendance Report - Manager'!H20 -> 0 | P20: =SUMIF(DailyAccomplishmentReport!$B$12:$B$26,B20,DailyAccomplishmentReport!$AP$12:$AP$26) -> 0 | Q20: =IF(C20<>"", (C20-$D$5)*24,0) -> -0.2 | R20: =IF(D20<>"", (D20-$E$5)*24,0) -> 0.066666667 | S20: =(ROUNDUP(Q20/0.5,0)*0.5 ) -> -0.5 | T20: =ROUND((D20-$D$5)*24,2) -> 9.07 | U20: =(D20-C20)*24 -> 9.2666667 | Z20: =VLOOKUP(B20,Ref!$F$3:$H$367,3,FALSE) -> #N/A | AA20: =SUMIF(DailyAccomplishmentReport!$B$12:$B$43,B20,DailyAccomplishmentReport!$D$12:$D$43) -> 0 | AB20: =IF(F20=$F$9,2,IF(AND(E20>=0,F20<=$F$8),(F20-E20)*24,IF(F20>$E$9,(F20-$E$9)*24,0))) -> 0 | AC20: =ROUND(AB20*$AC$11,2) -> 0 | AD20: =ROUND((F20-E20)*24,2) -> 0 | AE20: =VLOOKUP(Z20,Ref!$C$3:$D$14,2,) -> #N/A | AF20: =AD20*AE20 -> #N/A
B21: =B20+1 -> 45986 | C21: 8.3 | D21: 0.81875 | G21: 8 | H21: =IF(F21-E21*24=0,"",IF(ROUND((F21-E21)*24,2)>=6,ROUND((F21-E21)*24,2)-1,ROUND((F21-E21)*24,2))) | I21: assisted euronet and instapay testing | K21: =Billing!C31 -> 0 | L21: =Billing!D31 -> 0 | M21: ='Attendance Report - Manager'!G21 -> 0 | N21: ='Attendance Report - Manager'!H21 -> 0 | P21: =SUMIF(DailyAccomplishmentReport!$B$12:$B$26,B21,DailyAccomplishmentReport!$AP$12:$AP$26) -> 0 | Q21: =IF(C21<>"", (C21-$D$5)*24,0) -> 190.7 | R21: =IF(D21<>"", (D21-$E$5)*24,0) -> 2.15 | S21: =(ROUNDUP(Q21/0.5,0)*0.5 ) -> 191 | T21: =ROUND((D21-$D$5)*24,2) -> 11.15 | U21: =(D21-C21)*24 -> -179.55 | Z21: =VLOOKUP(B21,Ref!$F$3:$H$367,3,FALSE) -> #N/A | AA21: =SUMIF(DailyAccomplishmentReport!$B$12:$B$43,B21,DailyAccomplishmentReport!$D$12:$D$43) -> 0 | AB21: =IF(F21=$F$9,2,IF(AND(E21>=0,F21<=$F$8),(F21-E21)*24,IF(F21>$E$9,(F21-$E$9)*24,0))) -> 0 | AC21: =ROUND(AB21*$AC$11,2) -> 0 | AD21: =ROUND((F21-E21)*24,2) -> 0 | AE21: =VLOOKUP(Z21,Ref!$C$3:$D$14,2,) -> #N/A | AF21: =AD21*AE21 -> #N/A
B22: =B21+1 -> 45987 | C22: 0.35416667 | D22: 0.76111111 | G22: =IF(AND(C22="",D22=""),"",IF(AND(C22<=$D$5,D22>=$E$5),8, IF(AND(Q22<4,Q22>0,R22>=0),8-S22,IF(AND(Q22<4,C22>$D$5,U22>5),T22-(S22+1), IF(AND(Q22>3,D22<$E$5),T22-S22,IF(AND(Q22>3,D22>=$E$5),9-S22,IF(AND(C22>$D$5,U22<=4),T22-S22,IF(AND(C22>$D$5,U22>4),U22-(S22+1),IF(AND(C22<=$D$5,U22>=5),T22-1,IF(AND(C22<=$D$5,T22<=4),T22,IF(AND(C22<=$D$5,T22<5),4,IF(U22>5,U22-1,IF(U22<=4,U22,0))))))))))))) -> 8 | H22: =IF(F22-E22*24=0,"",IF(ROUND((F22-E22)*24,2)>=6,ROUND((F22-E22)*24,2)-1,ROUND((F22-E22)*24,2))) | I22: assisted euronet and instapay testing | K22: =Billing!C32 -> 0 | L22: =Billing!D32 -> 0 | M22: ='Attendance Report - Manager'!G22 -> 8 | N22: ='Attendance Report - Manager'!H22 -> 0 | P22: =SUMIF(DailyAccomplishmentReport!$B$12:$B$26,B22,DailyAccomplishmentReport!$AP$12:$AP$26) -> 0 | Q22: =IF(C22<>"", (C22-$D$5)*24,0) -> 0 | R22: =IF(D22<>"", (D22-$E$5)*24,0) -> 0.76666667 | S22: =(ROUNDUP(Q22/0.5,0)*0.5 ) -> 0 | T22: =ROUND((D22-$D$5)*24,2) -> 9.77 | U22: =(D22-C22)*24 -> 9.7666667 | Z22: =VLOOKUP(B22,Ref!$F$3:$H$367,3,FALSE) -> #N/A | AA22: =SUMIF(DailyAccomplishmentReport!$B$12:$B$43,B22,DailyAccomplishmentReport!$D$12:$D$43) -> 0 | AB22: =IF(F22=$F$9,2,IF(AND(E22>=0,F22<=$F$8),(F22-E22)*24,IF(F22>$E$9,(F22-$E$9)*24,0))) -> 0 | AC22: =ROUND(AB22*$AC$11,2) -> 0 | AD22: =ROUND((F22-E22)*24,2) -> 0 | AE22: =VLOOKUP(Z22,Ref!$C$3:$D$14,2,) -> #N/A | AF22: =AD22*AE22 -> #N/A
B23: 11/27/25 | C23: 9.35 | D23: 0.73888889 | G23: 8 | H23: =IF(F23-E23*24=0,"",IF(ROUND((F23-E23)*24,2)>=6,ROUND((F23-E23)*24,2)-1,ROUND((F23-E23)*24,2))) | I23: assisted euronet and instapay testing | K23: =Billing!C33 -> 0 | L23: =Billing!D33 -> 0 | M23: ='Attendance Report - Manager'!G23 -> 0 | N23: ='Attendance Report - Manager'!H23 -> 0 | P23: =SUMIF(DailyAccomplishmentReport!$B$12:$B$26,B23,DailyAccomplishmentReport!$AP$12:$AP$26) -> 0 | Q23: =IF(C23<>"", (C23-$D$5)*24,0) -> 215.9 | R23: =IF(D23<>"", (D23-$E$5)*24,0) -> 0.23333333 | S23: =(ROUNDUP(Q23/0.5,0)*0.5 ) -> 216 | T23: =ROUND((D23-$D$5)*24,2) -> 9.23 | U23: =(D23-C23)*24 -> -206.66667 | Z23: =VLOOKUP(B23,Ref!$F$3:$H$367,3,FALSE) -> #N/A | AA23: =SUMIF(DailyAccomplishmentReport!$B$12:$B$43,B23,DailyAccomplishmentReport!$D$12:$D$43) -> 0 | AB23: =IF(F23=$F$9,2,IF(AND(E23>=0,F23<=$F$8),(F23-E23)*24,IF(F23>$E$9,(F23-$E$9)*24,0))) -> 0 | AC23: =ROUND(AB23*$AC$11,2) -> 0 | AD23: =ROUND((F23-E23)*24,2) -> 0 | AE23: =VLOOKUP(Z23,Ref!$C$3:$D$14,2,) -> #N/A | AF23: =AD23*AE23 -> #N/A
B24: 11/28/25 | C24: 0.39583333 | D24: 0.82847222 | G24: 7 | I24: Worked on instapay dashboard's error | K24: =Billing!C34 -> 0 | L24: =Billing!D34 -> 0 | M24: ='Attendance Report - Manager'!G24 -> 8 | N24: ='Attendance Report - Manager'!H24 -> 0 | P24: =SUMIF(DailyAccomplishmentReport!$B$12:$B$26,B24,DailyAccomplishmentReport!$AP$12:$AP$26) -> 0 | Q24: =IF(C24<>"", (C24-$D$5)*24,0) -> 1 | R24: =IF(D24<>"", (D24-$E$5)*24,0) -> 2.3833333 | S24: =(ROUNDUP(Q24/0.5,0)*0.5 ) -> 1 | T24: =ROUND((D24-$D$5)*24,2) -> 11.38 | U24: =(D24-C24)*24 -> 10.383333 | Z24: =VLOOKUP(B24,Ref!$F$3:$H$367,3,FALSE) -> #N/A | AA24: =SUMIF(DailyAccomplishmentReport!$B$12:$B$43,B24,DailyAccomplishmentReport!$D$12:$D$43) -> 0 | AB24: =IF(F24=$F$9,2,IF(AND(E24>=0,F24<=$F$8),(F24-E24)*24,IF(F24>$E$9,(F24-$E$9)*24,0))) -> 0 | AC24: =ROUND(AB24*$AC$11,2) -> 0 | AD24: =ROUND((F24-E24)*24,2) -> 0 | AE24: =VLOOKUP(Z24,Ref!$C$3:$D$14,2,) -> #N/A | AF24: =AD24*AE24 -> #N/A
B25: 11/29/25 | H25: =IF(F25-E25*24=0,"",IF(ROUND((F25-E25)*24,2)>=6,ROUND((F25-E25)*24,2)-1,ROUND((F25-E25)*24,2))) | K25: =Billing!C35 -> 0 | L25: =Billing!D35 -> 0 | M25: ='Attendance Report - Manager'!G25 -> 0 | N25: ='Attendance Report - Manager'!H25 -> 0 | P25: =SUMIF(DailyAccomplishmentReport!$B$12:$B$26,B25,DailyAccomplishmentReport!$AP$12:$AP$26) -> 0 | Q25: =IF(C25<>"", (C25-$D$5)*24,0) -> 0 | R25: =IF(D25<>"", (D25-$E$5)*24,0) -> 0 | S25: =(ROUNDUP(Q25/0.5,0)*0.5 ) -> 0 | T25: =ROUND((D25-$D$5)*24,2) -> -8.5 | U25: =(D25-C25)*24 -> 0 | Z25: =VLOOKUP(B25,Ref!$F$3:$H$367,3,FALSE) -> #N/A | AA25: =SUMIF(DailyAccomplishmentReport!$B$12:$B$43,B25,DailyAccomplishmentReport!$D$12:$D$43) -> 0 | AB25: =IF(F25=$F$9,2,IF(AND(E25>=0,F25<=$F$8),(F25-E25)*24,IF(F25>$E$9,(F25-$E$9)*24,0))) -> 0 | AC25: =ROUND(AB25*$AC$11,2) -> 0 | AD25: =ROUND((F25-E25)*24,2) -> 0 | AE25: =VLOOKUP(Z25,Ref!$C$3:$D$14,2,) -> #N/A | AF25: =AD25*AE25 -> #N/A
B26: 11/30/25 | H26: =IF(F26-E26*24=0,"",IF(ROUND((F26-E26)*24,2)>=6,ROUND((F26-E26)*24,2)-1,ROUND((F26-E26)*24,2))) | K26: =Billing!C36 -> 0 | L26: =Billing!D36 -> 0 | M26: ='Attendance Report - Manager'!G26 -> 0 | N26: ='Attendance Report - Manager'!H26 -> 0 | P26: =SUMIF(DailyAccomplishmentReport!$B$12:$B$26,B26,DailyAccomplishmentReport!$AP$12:$AP$26) -> 0 | Q26: =IF(C26<>"", (C26-$D$5)*24,0) -> 0 | R26: =IF(D26<>"", (D26-$E$5)*24,0) -> 0 | S26: =(ROUNDUP(Q26/0.5,0)*0.5 ) -> 0 | T26: =ROUND((D26-$D$5)*24,2) -> -8.5 | U26: =(D26-C26)*24 -> 0 | Z26: =VLOOKUP(B26,Ref!$F$3:$H$367,3,FALSE) -> #N/A | AA26: =SUMIF(DailyAccomplishmentReport!$B$12:$B$43,B26,DailyAccomplishmentReport!$D$12:$D$43) -> 0 | AB26: =IF(F26=$F$9,2,IF(AND(E26>=0,F26<=$F$8),(F26-E26)*24,IF(F26>$E$9,(F26-$E$9)*24,0))) -> 0 | AC26: =ROUND(AB26*$AC$11,2) -> 0 | AD26: =ROUND((F26-E26)*24,2) -> 0 | AE26: =VLOOKUP(Z26,Ref!$C$3:$D$14,2,) -> #N/A | AF26: =AD26*AE26 -> #N/A
G27: =IF(AND(C27="",D27=""),"",IF(AND(C27<=$D$5,D27>=$E$5),8, IF(AND(Q27<4,Q27>0,R27>=0),8-S27,IF(AND(Q27<4,C27>$D$5,U27>5),T27-(S27+1), IF(AND(Q27>3,D27<$E$5),T27-S27,IF(AND(Q27>3,D27>=$E$5),9-S27,IF(AND(C27>$D$5,U27<=4),T27-S27,IF(AND(C27>$D$5,U27>4),U27-(S27+1),IF(AND(C27<=$D$5,U27>=5),T27-1,IF(AND(C27<=$D$5,T27<=4),T27,IF(AND(C27<=$D$5,T27<5),4,IF(U27>5,U27-1,IF(U27<=4,U27,0))))))))))))) | H27: =IF((AC27+AF27)=0,"",ROUND(AC27+AF27,2))
C28: Total | G28: =SUM(G12:G27) -> 79 | H28: =SUM(H12:H27) -> 0
B30: Certified Correct: | H30: Reviewed: Approved:
B32: =IF(DailyAccomplishmentReport!D3<>"",DailyAccomplishmentReport!D3,"") -> MIKAELLA ANDREA DEVELOS | H32: JUN M. SALVANERA | J32: HELEN D. PACIENCIA
B33: --------------------------------------------------------- | H33: ------------------------------------------- -----------------------------------------------
B34: Employee Signature over Printed Name | H34: Reviewed By Approved By
H35: (Signature over Printed Name) (Signature over Printed Name)

Sheet Attendance Report - Manager
B1: <Provider Logo>
B4: Name : | D4: =DailyAccomplishmentReport!D3:E3 -> MIKAELLA ANDREA DEVELOS
B5: Shift Schedule : | D5: ='Attendance Report_Second'!D5 -> 0.35416667 | E5: ='Attendance Report_Second'!E5 -> 0.72916667
B6: Client : | D6: Maybank Phil. Inc.
B7: Payroll Period : | D7: From | E7: To
D8: =DailyAccomplishmentReport!D8 -> 11/16/25 | E8: =DailyAccomplishmentReport!E8 -> 11/30/25
B10: Date | C10: Regular Hrs | E10: Overtime | G10: Total Hrs | I10: Remarks
C11: In | D11: Out | E11: In | F11: Out | G11: Regular | H11: OT
B12: =D8 -> 11/16/25 | C12: ='Attendance Report_Second'!C12 -> 0 | D12: ='Attendance Report_Second'!D12 -> 0 | E12: ='Attendance Report_Second'!E12 -> 0 | F12: ='Attendance Report_Second'!F12 -> 0 | G12: =IF(((D12-C12)*24-1)<0,0,IF(((D12-C12)*24)>9,8,ROUND(((D12-C12)*24-1),2))) -> 0 | H12: =IF(((F12-E12) *24 )>0,ROUND(((F12-E12) *24 ),2),0) -> 0 | K12: =Billing!C22 -> 0 | L12: =Billing!D22 -> 0
B13: =B12+1 -> #VALUE! | C13: ='Attendance Report_Second'!C13 -> 0.35416667 | D13: ='Attendance Report_Second'!D13 -> 0.76805556 | E13: ='Attendance Report_Second'!E13 -> 0 | F13: ='Attendance Report_Second'!F13 -> 0 | G13: =IF(((D13-C13)*24-1)<0,0,IF(((D13-C13)*24)>9,8,ROUND(((D13-C13)*24-1),2))) -> 8 | H13: =IF(((F13-E13) *24 )>0,ROUND(((F13-E13) *24 ),2),0) -> 0 | K13: =Billing!C23 -> 0 | L13: =Billing!D23 -> 0
B14: =B13+1 -> #VALUE! | C14: ='Attendance Report_Second'!C14 -> 0.34236111 | D14: ='Attendance Report_Second'!D14 -> 0.77361111 | E14: ='Attendance Report_Second'!E14 -> 0 | F14: ='Attendance Report_Second'!F14 -> 0 | G14: =IF(((D14-C14)*24-1)<0,0,IF(((D14-C14)*24)>9,8,ROUND(((D14-C14)*24-1),2))) -> 8 | H14: =IF(((F14-E14) *24 )>0,ROUND(((F14-E14) *24 ),2),0) -> 0 | K14: =Billing!C24 -> 0 | L14: =Billing!D24 -> 0
B15: =B14+1 -> #VALUE! | C15: ='Attendance Report_Second'!C15 -> 0.32708333 | D15: ='Attendance Report_Second'!D15 -> 0.7625 | E15: ='Attendance Report_Second'!E15 -> 0 | F15: ='Attendance Report_Second'!F15 -> 0 | G15: =IF(((D15-C15)*24-1)<0,0,IF(((D15-C15)*24)>9,8,ROUND(((D15-C15)*24-1),2))) -> 8 | H15: =IF(((F15-E15) *24 )>0,ROUND(((F15-E15) *24 ),2),0) -> 0 | K15: =Billing!C25 -> 0 | L15: =Billing!D25 -> 0
B16: =B15+1 -> #VALUE! | C16: ='Attendance Report_Second'!C16 -> 0.35416667 | D16: ='Attendance Report_Second'!D16 -> 0.79375 | E16: ='Attendance Report_Second'!E16 -> 0 | F16: ='Attendance Report_Second'!F16 -> 0 | G16: =IF(((D16-C16)*24-1)<0,0,IF(((D16-C16)*24)>9,8,ROUND(((D16-C16)*24-1),2))) -> 8 | H16: =IF(((F16-E16) *24 )>0,ROUND(((F16-E16) *24 ),2),0) -> 0 | K16: =Billing!C26 -> 0 | L16: =Billing!D26 -> 0
B17: =B16+1 -> #VALUE! | C17: ='Attendance Report_Second'!C17 -> 0.32083333 | D17: ='Attendance Report_Second'!D17 -> 0.74513889 | E17: ='Attendance Report_Second'!E17 -> 0 | F17: ='Attendance Report_Second'!F17 -> 0 | G17: =IF(((D17-C17)*24-1)<0,0,IF(((D17-C17)*24)>9,8,ROUND(((D17-C17)*24-1),2))) -> 8 | H17: =IF(((F17-E17) *24 )>0,ROUND(((F17-E17) *24 ),2),0) -> 0 | K17: =Billing!C27 -> 0 | L17: =Billing!D27 -> 0
B18: =B17+1 -> #VALUE! | C18: ='Attendance Report_Second'!C18 -> 0 | D18: ='Attendance Report_Second'!D18 -> 0 | E18: ='Attendance Report_Second'!E18 -> 0 | F18: ='Attendance Report_Second'!F18 -> 0 | G18: =IF(((D18-C18)*24-1)<0,0,IF(((D18-C18)*24)>9,8,ROUND(((D18-C18)*24-1),2))) -> 0 | H18: =IF(((F18-E18) *24 )>0,ROUND(((F18-E18) *24 ),2),0) -> 0 | K18: =Billing!C28 -> 0 | L18: =Billing!D28 -> 0
B19: =B18+1 -> #VALUE! | C19: ='Attendance Report_Second'!C19 -> 0 | D19: ='Attendance Report_Second'!D19 -> 0 | E19: ='Attendance Report_Second'!E19 -> 0 | F19: ='Attendance Report_Second'!F19 -> 0 | G19: =IF(((D19-C19)*24-1)<0,0,IF(((D19-C19)*24)>9,8,ROUND(((D19-C19)*24-1),2))) -> 0 | H19: =IF(((F19-E19) *24 )>0,ROUND(((F19-E19) *24 ),2),0) -> 0 | K19: =Billing!C29 -> 0 | L19: =Billing!D29 -> 0
B20: =B19+1 -> #VALUE! | C20: ='Attendance Report_Second'!C20 -> 0.34583333 | D20: ='Attendance Report_Second'!D20 -> 0.73194444 | E20: ='Attendance Report_Second'!E20 -> 0 | F20: ='Attendance Report_Second'!F20 -> 0 | G20: =IF(((D20-C20)*24-1)<0,0,IF(((D20-C20)*24)>9,8,ROUND(((D20-C20)*24-1),2))) -> 8 | H20: =IF(((F20-E20) *24 )>0,ROUND(((F20-E20) *24 ),2),0) -> 0 | K20: =Billing!C30 -> 0 | L20: =Billing!D30 -> 0
B21: =B20+1 -> #VALUE! | C21: ='Attendance Report_Second'!C21 -> 8.3 | D21: ='Attendance Report_Second'!D21 -> 0.81875 | E21: ='Attendance Report_Second'!E21 -> 0 | F21: ='Attendance Report_Second'!F21 -> 0 | G21: =IF(((D21-C21)*24-1)<0,0,IF(((D21-C21)*24)>9,8,ROUND(((D21-C21)*24-1),2))) -> 0 | H21: =IF(((F21-E21) *24 )>0,ROUND(((F21-E21) *24 ),2),0) -> 0 | K21: =Billing!C31 -> 0 | L21: =Billing!D31 -> 0
B22: =B21+1 -> #VALUE! | C22: ='Attendance Report_Second'!C22 -> 0.35416667 | D22: ='Attendance Report_Second'!D22 -> 0.76111111 | E22: ='Attendance Report_Second'!E22 -> 0 | F22: ='Attendance Report_Second'!F22 -> 0 | G22: =IF(((D22-C22)*24-1)<0,0,IF(((D22-C22)*24)>9,8,ROUND(((D22-C22)*24-1),2))) -> 8 | H22: =IF(((F22-E22) *24 )>0,ROUND(((F22-E22) *24 ),2),0) -> 0 | K22: =Billing!C32 -> 0 | L22: =Billing!D32 -> 0
B23: =B22+1 -> #VALUE! | C23: ='Attendance Report_Second'!C23 -> 9.35 | D23: ='Attendance Report_Second'!D23 -> 0.73888889 | E23: ='Attendance Report_Second'!E23 -> 0 | F23: ='Attendance Report_Second'!F23 -> 0 | G23: =IF(((D23-C23)*24-1)<0,0,IF(((D23-C23)*24)>9,8,ROUND(((D23-C23)*24-1),2))) -> 0 | H23: =IF(((F23-E23) *24 )>0,ROUND(((F23-E23) *24 ),2),0) -> 0 | K23: =Billing!C33 -> 0 | L23: =Billing!D33 -> 0
B24: =B23+1 -> #VALUE! | C24: ='Attendance Report_Second'!C24 -> 0.39583333 | D24: ='Attendance Report_Second'!D24 -> 0.82847222 | E24: ='Attendance Report_Second'!E24 -> 0 | F24: ='Attendance Report_Second'!F24 -> 0 | G24: =IF(((D24-C24)*24-1)<0,0,IF(((D24-C24)*24)>9,8,ROUND(((D24-C24)*24-1),2))) -> 8 | H24: =IF(((F24-E24) *24 )>0,ROUND(((F24-E24) *24 ),2),0) -> 0 | K24: =Billing!C34 -> 0 | L24: =Billing!D34 -> 0
... B26: =B25+1 -> #VALUE! | C26: ='Attendance Report_Second'!C26 -> 0 | D26: ='Attendance Report_Second'!D26 -> 0 | E26: ='Attendance Report_Second'!E26 -> 0 | F26: ='Attendance Report_Second'!F26 -> 0 | G26: =IF(((D26-C26)*24-1)<0,0,IF(((D26-C26)*24)>9,8,ROUND(((D26-C26)*24-1),2))) -> 0 | H26: =IF(((F26-E26) *24 )>0,ROUND(((F26-E26) *24 ),2),0) -> 0 | K26: =Billing!C36 -> 0 | L26: =Billing!D36 -> 0
B27: =B26+1 -> #VALUE! | C27: ='Attendance Report__First'!C12 -> 0 | D27: ='Attendance Report__First'!D12 -> 0 | E27: ='Attendance Report__First'!E12 -> 0 | F27: ='Attendance Report__First'!F12 -> 0 | G27: =IF(((D27-C27)*24-1)<0,0,IF(((D27-C27)*24)>9,8,ROUND(((D27-C27)*24-1),2))) -> 0 | H27: =IF(((F27-E27) *24 )>0,ROUND(((F27-E27) *24 ),2),0) -> 0 | K27: =Billing!C37 -> 0 | L27: =Billing!D37 -> 0
B28: =B27+1 -> #VALUE! | C28: ='Attendance Report__First'!C13 -> 0 | D28: ='Attendance Report__First'!D13 -> 0 | E28: ='Attendance Report__First'!E13 -> 0 | F28: ='Attendance Report__First'!F13 -> 0 | G28: =IF(((D28-C28)*24-1)<0,0,IF(((D28-C28)*24)>9,8,ROUND(((D28-C28)*24-1),2))) -> 0 | H28: =IF(((F28-E28) *24 )>0,ROUND(((F28-E28) *24 ),2),0) -> 0 | K28: =Billing!C38 -> 0 | L28: =Billing!D38 -> 0
B29: =B28+1 -> #VALUE! | C29: ='Attendance Report__First'!C14 -> 0.32361111 | D29: ='Attendance Report__First'!D14 -> 0.73263889 | E29: ='Attendance Report__First'!E14 -> 0 | F29: ='Attendance Report__First'!F14 -> 0 | G29: =IF(((D29-C29)*24-1)<0,0,IF(((D29-C29)*24)>9,8,ROUND(((D29-C29)*24-1),2))) -> 8 | H29: =IF(((F29-E29) *24 )>0,ROUND(((F29-E29) *24 ),2),0) -> 0 | K29: =Billing!C39 -> 0 | L29: =Billing!D39 -> 0
B30: =B29+1 -> #VALUE! | C30: ='Attendance Report__First'!C15 -> 0.33819444 | D30: ='Attendance Report__First'!D15 -> 0.73125 | E30: ='Attendance Report__First'!E15 -> 0 | F30: ='Attendance Report__First'!F15 -> 0 | G30: =IF(((D30-C30)*24-1)<0,0,IF(((D30-C30)*24)>9,8,ROUND(((D30-C30)*24-1),2))) -> 8 | H30: =IF(((F30-E30) *24 )>0,ROUND(((F30-E30) *24 ),2),0) -> 0 | K30: =Billing!C40 -> 0 | L30: =Billing!D40 -> 0
B31: =B30+1 -> #VALUE! | C31: ='Attendance Report__First'!C16 -> 0.325 | D31: ='Attendance Report__First'!D16 -> 0.72916667 | E31: ='Attendance Report__First'!E16 -> 0 | F31: ='Attendance Report__First'!F16 -> 0 | G31: =IF(((D31-C31)*24-1)<0,0,IF(((D31-C31)*24)>9,8,ROUND(((D31-C31)*24-1),2))) -> 8 | H31: =IF(((F31-E31) *24 )>0,ROUND(((F31-E31) *24 ),2),0) -> 0 | K31: =Billing!C41 -> 0 | L31: =Billing!D41 -> 0
B32: =B31+1 -> #VALUE! | C32: ='Attendance Report__First'!C17 -> 0.33402778 | D32: ='Attendance Report__First'!D17 -> 0.72916667 | E32: ='Attendance Report__First'!E17 -> 0 | F32: ='Attendance Report__First'!F17 -> 0 | G32: =IF(((D32-C32)*24-1)<0,0,IF(((D32-C32)*24)>9,8,ROUND(((D32-C32)*24-1),2))) -> 8 | H32: =IF(((F32-E32) *24 )>0,ROUND(((F32-E32) *24 ),2),0) -> 0 | K32: =Billing!C42 -> 0 | L32: =Billing!D42 -> 0
B33: =B32+1 -> #VALUE! | C33: ='Attendance Report__First'!C18 -> 0.30069444 | D33: ='Attendance Report__First'!D18 -> 0.73541667 | E33: ='Attendance Report__First'!E18 -> 0 | F33: ='Attendance Report__First'!F18 -> 0 | G33: =IF(((D33-C33)*24-1)<0,0,IF(((D33-C33)*24)>9,8,ROUND(((D33-C33)*24-1),2))) -> 8 | H33: =IF(((F33-E33) *24 )>0,ROUND(((F33-E33) *24 ),2),0) -> 0 | K33: =Billing!C43 -> 0 | L33: =Billing!D43 -> 0
B34: =B33+1 -> #VALUE! | C34: ='Attendance Report__First'!C19 -> 0 | D34: ='Attendance Report__First'!D19 -> 0 | E34: ='Attendance Report__First'!E19 -> 0 | F34: ='Attendance Report__First'!F19 -> 0 | G34: =IF(((D34-C34)*24-1)<0,0,IF(((D34-C34)*24)>9,8,ROUND(((D34-C34)*24-1),2))) -> 0 | H34: =IF(((F34-E34) *24 )>0,ROUND(((F34-E34) *24 ),2),0) -> 0 | K34: =Billing!C44 -> 0 | L34: =Billing!D44 -> 0
B35: =B34+1 -> #VALUE! | C35: ='Attendance Report__First'!C20 -> 0 | D35: ='Attendance Report__First'!D20 -> 0 | E35: ='Attendance Report__First'!E20 -> 0 | F35: ='Attendance Report__First'!F20 -> 0 | G35: =IF(((D35-C35)*24-1)<0,0,IF(((D35-C35)*24)>9,8,ROUND(((D35-C35)*24-1),2))) -> 0 | H35: =IF(((F35-E35) *24 )>0,ROUND(((F35-E35) *24 ),2),0) -> 0 | K35: =Billing!C45 -> 0 | L35: =Billing!D45 -> 0
B36: =B35+1 -> #VALUE! | C36: ='Attendance Report__First'!C21 -> 0 | D36: ='Attendance Report__First'!D21 -> 0 | E36: ='Attendance Report__First'!E21 -> 0 | F36: ='Attendance Report__First'!F21 -> 0 | G36: =IF(((D36-C36)*24-1)<0,0,IF(((D36-C36)*24)>9,8,ROUND(((D36-C36)*24-1),2))) -> 0 | H36: =IF(((F36-E36) *24 )>0,ROUND(((F36-E36) *24 ),2),0) -> 0 | K36: =Billing!C46 -> 0 | L36: =Billing!D46 -> 0
B37: =B36+1 -> #VALUE! | C37: ='Attendance Report__First'!C22 -> 0.33263889 | D37: ='Attendance Report__First'!D22 -> 0.72916667 | E37: ='Attendance Report__First'!E22 -> 0 | F37: ='Attendance Report__First'!F22 -> 0 | G37: =IF(((D37-C37)*24-1)<0,0,IF(((D37-C37)*24)>9,8,ROUND(((D37-C37)*24-1),2))) -> 8 | H37: =IF(((F37-E37) *24 )>0,ROUND(((F37-E37) *24 ),2),0) -> 0 | K37: =Billing!C47 -> 0 | L37: =Billing!D47 -> 0
B38: =B37+1 -> #VALUE! | C38: ='Attendance Report__First'!C23 -> 0.325 | D38: ='Attendance Report__First'!D23 -> 0.63888889 | E38: ='Attendance Report__First'!E23 -> 0 | F38: ='Attendance Report__First'!F23 -> 0 | G38: =IF(((D38-C38)*24-1)<0,0,IF(((D38-C38)*24)>9,8,ROUND(((D38-C38)*24-1),2))) -> 6.53 | H38: =IF(((F38-E38) *24 )>0,ROUND(((F38-E38) *24 ),2),0) -> 0 | K38: =Billing!C48 -> 0 | L38: =Billing!D48 -> 0
... B41: =B40+1 -> #VALUE! | C41: ='Attendance Report__First'!C26 -> 0 | D41: ='Attendance Report__First'!D26 -> 0 | E41: ='Attendance Report__First'!E26 -> 0 | F41: ='Attendance Report__First'!F26 -> 0 | G41: =IF(((D41-C41)*24-1)<0,0,IF(((D41-C41)*24)>9,8,ROUND(((D41-C41)*24-1),2))) -> 0 | H41: =IF(((F41-E41) *24 )>0,ROUND(((F41-E41) *24 ),2),0) -> 0 | K41: =Billing!C51 -> 0 | L41: =Billing!D51 -> 0
B42: =B41+1 -> #VALUE! | C42: ='Attendance Report__First'!#REF! -> #REF! | D42: ='Attendance Report__First'!#REF! -> #REF! | E42: ='Attendance Report__First'!#REF! -> #REF! | F42: ='Attendance Report__First'!#REF! -> #REF! | G42: =IF(((D42-C42)*24-1)<0,0,IF(((D42-C42)*24)>9,8,ROUND(((D42-C42)*24-1),2))) -> #REF! | H42: =IF(((F42-E42) *24 )>0,ROUND(((F42-E42) *24 ),2),0) -> #REF! | K42: =Billing!C52 -> 0 | L42: =Billing!D52 -> 0
B45: Certified Correct: | H45: Reviewed/Noted:
B47: ____________________________________ | H47: _______________________________
B48: Employee Signature over Printed Name | H48: Department Head
H49: (Signature over Printed Name)

Sheet Billing
B1: DAILY TIME RECORD (Total Number of Working Hours per Cost Center)
I3: TOTAL NUMBER OF WORKING HOURS PER COST CENTER | V3: DETAILED TOTAL NUMBER OF WORKING HOURS/COST OF BUDGET PER COST CENTER
B4: Name : | D4: =IF(DailyAccomplishmentReport!D3<>"",DailyAccomplishmentReport!D3,"") -> MIKAELLA ANDREA DEVELOS | I4: Cost Center | J4: Number of Hours | M4: Total Cost | P4: 12% VAT | Q4: Final Cost
B5: =DailyAccomplishmentReport!B4:C4 -> Provider : | D5: =IF(DailyAccomplishmentReport!D4<>"",DailyAccomplishmentReport!D4,"") -> RADIX | J5: Regular | K5: OT | L5: OT % | M5: Regular | N5: OT | O5: Total | V5: Cost Center | W5: Budget To Be Drawn Form | X5: Regular Hours | Y5: Regular Hrs(Cost) | Z5: OT Hours | AA5: OT Hrs(Cost) | AB5: Total Costs | AC5: VAT (12%) | AD5: Final Costs
B6: Team Lead : | D6: =IF(DailyAccomplishmentReport!D5<>"",DailyAccomplishmentReport!D5,"") -> Jun M. Salvanera | I6: {=IFERROR(INDEX(list1,MATCH(0,COUNTIF($I$5:I5,list1)+IF(COUNTIF(list1,list1)>1,0,1),0)),"")} -> OP - IT | J6: =SUMIF(DailyAccomplishmentReport!$S$12:$S$27,Billing!I6,DailyAccomplishmentReport!$C$12:$C$26) -> 69.83 | K6: =SUMIF(DailyAccomplishmentReport!$S$12:$S$27,Billing!I6,DailyAccomplishmentReport!$AP$12:$AP$26) -> 0 | L6: =IFERROR(SUMIF(DailyAccomplishmentReport!$S$12:$S$27,Billing!I6,DailyAccomplishmentReport!$X$12:$X$26),0) -> 0 | M6: =J6*$E$10 -> 0 | N6: =$E$10*K6 -> 0 | O6: =N6+M6 -> 0 | P6: =O6*$S$20 -> 0 | Q6: =P6+O6 -> 0 | V6: 0 | W6: 0 | X6: 0 | Y6: 0 | Z6: 0 | AA6: 0 | AB6: 0 | AC6: 0 | AD6: 0
B7: Section/Unit : | D7: =IF(DailyAccomplishmentReport!D6<>"",DailyAccomplishmentReport!D6,"") -> BD1 | I7: {=IFERROR(INDEX(list1,MATCH(0,COUNTIF($I$5:I6,list1)+IF(COUNTIF(list1,list1)>1,0,1),0)),"")} | J7: =SUMIF(DailyAccomplishmentReport!$S$12:$S$27,Billing!I7,DailyAccomplishmentReport!$C$12:$C$26) -> 0 | K7: =SUMIF(DailyAccomplishmentReport!$S$12:$S$27,Billing!I7,DailyAccomplishmentReport!$AP$12:$AP$26) -> 0 | L7: =IFERROR(SUMIF(DailyAccomplishmentReport!$S$12:$S$27,Billing!I7,DailyAccomplishmentReport!$X$12:$X$26),0) -> 0 | M7: =J7*$E$10 -> 0 | N7: =$E$10*K7 -> 0 | O7: =N7+M7 -> 0 | P7: =O7*$S$20 -> 0 | Q7: =P7+O7 -> 0 | V7: 0 Total | X7: 0 | Y7: 0 | Z7: 0 | AA7: 0 | AB7: 0 | AC7: 0 | AD7: 0
B8: Payroll Period : | D8: From | E8: To | I8: {=IFERROR(INDEX(list1,MATCH(0,COUNTIF($I$5:I7,list1)+IF(COUNTIF(list1,list1)>1,0,1),0)),"")} | J8: =SUMIF(DailyAccomplishmentReport!$S$12:$S$27,Billing!I8,DailyAccomplishmentReport!$C$12:$C$26) -> 0 | K8: =SUMIF(DailyAccomplishmentReport!$S$12:$S$27,Billing!I8,DailyAccomplishmentReport!$AP$12:$AP$26) -> 0 | L8: =IFERROR(SUMIF(DailyAccomplishmentReport!$S$12:$S$27,Billing!I8,DailyAccomplishmentReport!$X$12:$X$26),0) -> 0 | M8: =J8*$E$10 -> 0 | N8: =$E$10*K8 -> 0 | O8: =N8+M8 -> 0 | P8: =O8*$S$20 -> 0 | Q8: =P8+O8 -> 0 | V8: Grand Total | X8: 0 | Y8: 0 | Z8: 0 | AA8: 0 | AB8: 0 | AC8: 0 | AD8: 0
D9: =DailyAccomplishmentReport!D8 -> 11/16/25 | E9: =DailyAccomplishmentReport!E8 -> 11/30/25 | I9: {=IFERROR(INDEX(list1,MATCH(0,COUNTIF($I$5:I8,list1)+IF(COUNTIF(list1,list1)>1,0,1),0)),"")} | J9: =SUMIF(DailyAccomplishmentReport!$S$12:$S$27,Billing!I9,DailyAccomplishmentReport!$C$12:$C$26) -> 0 | K9: =SUMIF(DailyAccomplishmentReport!$S$12:$S$27,Billing!I9,DailyAccomplishmentReport!$AP$12:$AP$26) -> 0 | L9: =IFERROR(SUMIF(DailyAccomplishmentReport!$S$12:$S$27,Billing!I9,DailyAccomplishmentReport!$X$12:$X$26),0) -> 0 | M9: =J9*$E$10 -> 0 | N9: =$E$10*K9 -> 0 | O9: =N9+M9 -> 0 | P9: =O9*$S$20 -> 0 | Q9: =P9+O9 -> 0
B10: Hourly Rate : | D10: PHP | I10: {=IFERROR(INDEX(list1,MATCH(0,COUNTIF($I$5:I9,list1)+IF(COUNTIF(list1,list1)>1,0,1),0)),"")} | J10: =SUMIF(DailyAccomplishmentReport!$S$12:$S$27,Billing!I10,DailyAccomplishmentReport!$C$12:$C$26) -> 0 | K10: =SUMIF(DailyAccomplishmentReport!$S$12:$S$27,Billing!I10,DailyAccomplishmentReport!$AP$12:$AP$26) -> 0 | L10: =IFERROR(SUMIF(DailyAccomplishmentReport!$S$12:$S$27,Billing!I10,DailyAccomplishmentReport!$X$12:$X$26),0) -> 0 | M10: =J10*$E$10 -> 0 | N10: =$E$10*K10 -> 0 | O10: =N10+M10 -> 0 | P10: =O10*$S$20 -> 0 | Q10: =P10+O10 -> 0
I11: {=IFERROR(INDEX(list1,MATCH(0,COUNTIF($I$5:I10,list1)+IF(COUNTIF(list1,list1)>1,0,1),0)),"")} | J11: =SUMIF(DailyAccomplishmentReport!$S$12:$S$27,Billing!I11,DailyAccomplishmentReport!$C$12:$C$26) -> 0 | K11: =SUMIF(DailyAccomplishmentReport!$S$12:$S$27,Billing!I11,DailyAccomplishmentReport!$AP$12:$AP$26) -> 0 | L11: =IFERROR(SUMIF(DailyAccomplishmentReport!$S$12:$S$27,Billing!I11,DailyAccomplishmentReport!$X$12:$X$26),0) -> 0 | M11: =J11*$E$10 -> 0 | N11: =$E$10*K11 -> 0 | O11: =N11+M11 -> 0 | P11: =O11*$S$20 -> 0 | Q11: =P11+O11 -> 0
I12: {=IFERROR(INDEX(list1,MATCH(0,COUNTIF($I$5:I11,list1)+IF(COUNTIF(list1,list1)>1,0,1),0)),"")} | J12: =SUMIF(DailyAccomplishmentReport!$S$12:$S$27,Billing!I12,DailyAccomplishmentReport!$C$12:$C$26) -> 0 | K12: =SUMIF(DailyAccomplishmentReport!$S$12:$S$27,Billing!I12,DailyAccomplishmentReport!$AP$12:$AP$26) -> 0 | L12: =IFERROR(SUMIF(DailyAccomplishmentReport!$S$12:$S$27,Billing!I12,DailyAccomplishmentReport!$X$12:$X$26),0) -> 0 | M12: =J12*$E$10 -> 0 | N12: =$E$10*K12 -> 0 | O12: =N12+M12 -> 0 | P12: =O12*$S$20 -> 0 | Q12: =P12+O12 -> 0
I13: {=IFERROR(INDEX(list1,MATCH(0,COUNTIF($I$5:I12,list1)+IF(COUNTIF(list1,list1)>1,0,1),0)),"")} | J13: =SUMIF(DailyAccomplishmentReport!$S$12:$S$27,Billing!I13,DailyAccomplishmentReport!$C$12:$C$26) -> 0 | K13: =SUMIF(DailyAccomplishmentReport!$S$12:$S$27,Billing!I13,DailyAccomplishmentReport!$AP$12:$AP$26) -> 0 | L13: =IFERROR(SUMIF(DailyAccomplishmentReport!$S$12:$S$27,Billing!I13,DailyAccomplishmentReport!$X$12:$X$26),0) -> 0 | M13: =J13*$E$10 -> 0 | N13: =$E$10*K13 -> 0 | O13: =N13+M13 -> 0 | P13: =O13*$S$20 -> 0 | Q13: =P13+O13 -> 0
I14: {=IFERROR(INDEX(list1,MATCH(0,COUNTIF($I$5:I13,list1)+IF(COUNTIF(list1,list1)>1,0,1),0)),"")} | J14: =SUMIF(DailyAccomplishmentReport!$S$12:$S$27,Billing!I14,DailyAccomplishmentReport!$C$12:$C$26) -> 0 | K14: =SUMIF(DailyAccomplishmentReport!$S$12:$S$27,Billing!I14,DailyAccomplishmentReport!$AP$12:$AP$26) -> 0 | L14: =IFERROR(SUMIF(DailyAccomplishmentReport!$S$12:$S$27,Billing!I14,DailyAccomplishmentReport!$X$12:$X$26),0) -> 0 | M14: =J14*$E$10 -> 0 | N14: =$E$10*K14 -> 0 | O14: =N14+M14 -> 0 | P14: =O14*$S$20 -> 0 | Q14: =P14+O14 -> 0
I15: {=IFERROR(INDEX(list1,MATCH(0,COUNTIF($I$5:I14,list1)+IF(COUNTIF(list1,list1)>1,0,1),0)),"")} | J15: =SUMIF(DailyAccomplishmentReport!$S$12:$S$27,Billing!I15,DailyAccomplishmentReport!$C$12:$C$26) -> 0 | K15: =SUMIF(DailyAccomplishmentReport!$S$12:$S$27,Billing!I15,DailyAccomplishmentReport!$AP$12:$AP$26) -> 0 | L15: =IFERROR(SUMIF(DailyAccomplishmentReport!$S$12:$S$27,Billing!I15,DailyAccomplishmentReport!$X$12:$X$26),0) -> 0 | M15: =J15*$E$10 -> 0 | N15: =$E$10*K15 -> 0 | O15: =N15+M15 -> 0 | P15: =O15*$S$20 -> 0 | Q15: =P15+O15 -> 0
I16: {=IFERROR(INDEX(list1,MATCH(0,COUNTIF($I$5:I15,list1)+IF(COUNTIF(list1,list1)>1,0,1),0)),"")} | J16: =SUMIF(DailyAccomplishmentReport!$S$12:$S$27,Billing!I16,DailyAccomplishmentReport!$C$12:$C$26) -> 0 | K16: =SUMIF(DailyAccomplishmentReport!$S$12:$S$27,Billing!I16,DailyAccomplishmentReport!$AP$12:$AP$26) -> 0 | L16: =IFERROR(SUMIF(DailyAccomplishmentReport!$S$12:$S$27,Billing!I16,DailyAccomplishmentReport!$X$12:$X$26),0) -> 0 | M16: =J16*$E$10 -> 0 | N16: =$E$10*K16 -> 0 | O16: =N16+M16 -> 0 | P16: =O16*$S$20 -> 0 | Q16: =P16+O16 -> 0
I17: {=IFERROR(INDEX(list1,MATCH(0,COUNTIF($I$5:I16,list1)+IF(COUNTIF(list1,list1)>1,0,1),0)),"")} | J17: =SUMIF(DailyAccomplishmentReport!$S$12:$S$27,Billing!I17,DailyAccomplishmentReport!$C$12:$C$26) -> 0 | K17: =SUMIF(DailyAccomplishmentReport!$S$12:$S$27,Billing!I17,DailyAccomplishmentReport!$AP$12:$AP$26) -> 0 | L17: =IFERROR(SUMIF(DailyAccomplishmentReport!$S$12:$S$27,Billing!I17,DailyAccomplishmentReport!$X$12:$X$26),0) -> 0 | M17: =J17*$E$10 -> 0 | N17: =$E$10*K17 -> 0 | O17: =N17+M17 -> 0 | P17: =O17*$S$20 -> 0 | Q17: =P17+O17 -> 0
I18: Total | J18: =SUM(J6:J17) -> 69.83 | K18: =SUM(K6:K17) -> 0 | L18: =SUM(L6:L17) -> 0 | M18: =SUM(M6:M17) -> 0 | N18: =SUM(N6:N17) -> 0 | O18: =SUM(O6:O17) -> 0 | P18: =SUM(P6:P17) -> 0 | Q18: =SUM(Q6:Q17) -> 0
B20: Date | C20: Number of Hours | E20: Total Cost | H20: Description/Comments | S20: 0.12
C21: Regular | D21: OT | E21: Regular | F21: OT | G21: Total
B22: =D9 -> 11/16/25 | C22: =SUMIF(DailyAccomplishmentReport!$B$12:$B$26,Billing!B22,DailyAccomplishmentReport!$C$12:$C$26) -> 0 | D22: =SUMIF(DailyAccomplishmentReport!$B$12:$B$26,Billing!B22,DailyAccomplishmentReport!$AP$12:$AP$26) -> 0 | E22: =$E$10*C22 -> 0 | F22: =IFERROR($E$10*S22*D22,0) -> 0 | G22: =F22+E22 -> 0 | S22: =VLOOKUP(T22,Ref!$C$3:$D$14,2,FALSE) -> #N/A | T22: =VLOOKUP(B22,Ref!$F$3:$H$367,3,FALSE) -> #N/A | U22: =SUMIF(DailyAccomplishmentReport!$B$12:$B$43,Billing!B22,DailyAccomplishmentReport!$C$12:$C$43) -> 0
B23: =B22+1 -> #VALUE! | C23: =SUMIF(DailyAccomplishmentReport!$B$12:$B$26,Billing!B23,DailyAccomplishmentReport!$C$12:$C$26) -> 0 | D23: =SUMIF(DailyAccomplishmentReport!$B$12:$B$26,Billing!B23,DailyAccomplishmentReport!$AP$12:$AP$26) -> 0 | E23: =$E$10*C23 -> 0 | F23: =IFERROR($E$10*S23*D23,0) -> 0 | G23: =F23+E23 -> 0 | S23: =VLOOKUP(T23,Ref!$C$3:$D$14,2,FALSE) -> #VALUE! | T23: =VLOOKUP(B23,Ref!$F$3:$H$367,3,FALSE) -> #VALUE! | U23: =SUMIF(DailyAccomplishmentReport!$B$12:$B$43,Billing!B23,DailyAccomplishmentReport!$C$12:$C$43) -> 0
B24: =B23+1 -> #VALUE! | C24: =SUMIF(DailyAccomplishmentReport!$B$12:$B$26,Billing!B24,DailyAccomplishmentReport!$C$12:$C$26) -> 0 | D24: =SUMIF(DailyAccomplishmentReport!$B$12:$B$26,Billing!B24,DailyAccomplishmentReport!$AP$12:$AP$26) -> 0 | E24: =$E$10*C24 -> 0 | F24: =IFERROR($E$10*S24*D24,0) -> 0 | G24: =F24+E24 -> 0 | S24: =VLOOKUP(T24,Ref!$C$3:$D$14,2,FALSE) -> #VALUE! | T24: =VLOOKUP(B24,Ref!$F$3:$H$367,3,FALSE) -> #VALUE! | U24: =SUMIF(DailyAccomplishmentReport!$B$12:$B$43,Billing!B24,DailyAccomplishmentReport!$C$12:$C$43) -> 0
B25: =B24+1 -> #VALUE! | C25: =SUMIF(DailyAccomplishmentReport!$B$12:$B$26,Billing!B25,DailyAccomplishmentReport!$C$12:$C$26) -> 0 | D25: =SUMIF(DailyAccomplishmentReport!$B$12:$B$26,Billing!B25,DailyAccomplishmentReport!$AP$12:$AP$26) -> 0 | E25: =$E$10*C25 -> 0 | F25: =IFERROR($E$10*S25*D25,0) -> 0 | G25: =F25+E25 -> 0 | S25: =VLOOKUP(T25,Ref!$C$3:$D$14,2,FALSE) -> #VALUE! | T25: =VLOOKUP(B25,Ref!$F$3:$H$367,3,FALSE) -> #VALUE! | U25: =SUMIF(DailyAccomplishmentReport!$B$12:$B$43,Billing!B25,DailyAccomplishmentReport!$C$12:$C$43) -> 0
B26: =B25+1 -> #VALUE! | C26: =SUMIF(DailyAccomplishmentReport!$B$12:$B$26,Billing!B26,DailyAccomplishmentReport!$C$12:$C$26) -> 0 | D26: =SUMIF(DailyAccomplishmentReport!$B$12:$B$26,Billing!B26,DailyAccomplishmentReport!$AP$12:$AP$26) -> 0 | E26: =$E$10*C26 -> 0 | F26: =IFERROR($E$10*S26*D26,0) -> 0 | G26: =F26+E26 -> 0 | S26: =VLOOKUP(T26,Ref!$C$3:$D$14,2,FALSE) -> #VALUE! | T26: =VLOOKUP(B26,Ref!$F$3:$H$367,3,FALSE) -> #VALUE! | U26: =SUMIF(DailyAccomplishmentReport!$B$12:$B$43,Billing!B26,DailyAccomplishmentReport!$C$12:$C$43) -> 0
B27: =B26+1 -> #VALUE! | C27: =SUMIF(DailyAccomplishmentReport!$B$12:$B$26,Billing!B27,DailyAccomplishmentReport!$C$12:$C$26) -> 0 | D27: =SUMIF(DailyAccomplishmentReport!$B$12:$B$26,Billing!B27,DailyAccomplishmentReport!$AP$12:$AP$26) -> 0 | E27: =$E$10*C27 -> 0 | F27: =IFERROR($E$10*S27*D27,0) -> 0 | G27: =F27+E27 -> 0 | S27: =VLOOKUP(T27,Ref!$C$3:$D$14,2,FALSE) -> #VALUE! | T27: =VLOOKUP(B27,Ref!$F$3:$H$367,3,FALSE) -> #VALUE! | U27: =SUMIF(DailyAccomplishmentReport!$B$12:$B$43,Billing!B27,DailyAccomplishmentReport!$C$12:$C$43) -> 0
B28: =B27+1 -> #VALUE! | C28: =SUMIF(DailyAccomplishmentReport!$B$12:$B$26,Billing!B28,DailyAccomplishmentReport!$C$12:$C$26) -> 0 | D28: =SUMIF(DailyAccomplishmentReport!$B$12:$B$26,Billing!B28,DailyAccomplishmentReport!$AP$12:$AP$26) -> 0 | E28: =$E$10*C28 -> 0 | F28: =IFERROR($E$10*S28*D28,0) -> 0 | G28: =F28+E28 -> 0 | S28: =VLOOKUP(T28,Ref!$C$3:$D$14,2,FALSE) -> #VALUE! | T28: =VLOOKUP(B28,Ref!$F$3:$H$367,3,FALSE) -> #VALUE! | U28: =SUMIF(DailyAccomplishmentReport!$B$12:$B$43,Billing!B28,DailyAccomplishmentReport!$C$12:$C$43) -> 0
B29: =B28+1 -> #VALUE! | C29: =SUMIF(DailyAccomplishmentReport!$B$12:$B$26,Billing!B29,DailyAccomplishmentReport!$C$12:$C$26) -> 0 | D29: =SUMIF(DailyAccomplishmentReport!$B$12:$B$26,Billing!B29,DailyAccomplishmentReport!$AP$12:$AP$26) -> 0 | E29: =$E$10*C29 -> 0 | F29: =IFERROR($E$10*S29*D29,0) -> 0 | G29: =F29+E29 -> 0 | S29: =VLOOKUP(T29,Ref!$C$3:$D$14,2,FALSE) -> #VALUE! | T29: =VLOOKUP(B29,Ref!$F$3:$H$367,3,FALSE) -> #VALUE! | U29: =SUMIF(DailyAccomplishmentReport!$B$12:$B$43,Billing!B29,DailyAccomplishmentReport!$C$12:$C$43) -> 0
B30: =B29+1 -> #VALUE! | C30: =SUMIF(DailyAccomplishmentReport!$B$12:$B$26,Billing!B30,DailyAccomplishmentReport!$C$12:$C$26) -> 0 | D30: =SUMIF(DailyAccomplishmentReport!$B$12:$B$26,Billing!B30,DailyAccomplishmentReport!$AP$12:$AP$26) -> 0 | E30: =$E$10*C30 -> 0 | F30: =IFERROR($E$10*S30*D30,0) -> 0 | G30: =F30+E30 -> 0 | S30: =VLOOKUP(T30,Ref!$C$3:$D$14,2,FALSE) -> #VALUE! | T30: =VLOOKUP(B30,Ref!$F$3:$H$367,3,FALSE) -> #VALUE! | U30: =SUMIF(DailyAccomplishmentReport!$B$12:$B$43,Billing!B30,DailyAccomplishmentReport!$C$12:$C$43) -> 0
B31: =B30+1 -> #VALUE! | C31: =SUMIF(DailyAccomplishmentReport!$B$12:$B$26,Billing!B31,DailyAccomplishmentReport!$C$12:$C$26) -> 0 | D31: =SUMIF(DailyAccomplishmentReport!$B$12:$B$26,Billing!B31,DailyAccomplishmentReport!$AP$12:$AP$26) -> 0 | E31: =$E$10*C31 -> 0 | F31: =IFERROR($E$10*S31*D31,0) -> 0 | G31: =F31+E31 -> 0 | S31: =VLOOKUP(T31,Ref!$C$3:$D$14,2,FALSE) -> #VALUE! | T31: =VLOOKUP(B31,Ref!$F$3:$H$367,3,FALSE) -> #VALUE! | U31: =SUMIF(DailyAccomplishmentReport!$B$12:$B$43,Billing!B31,DailyAccomplishmentReport!$C$12:$C$43) -> 0
B32: =B31+1 -> #VALUE! | C32: =SUMIF(DailyAccomplishmentReport!$B$12:$B$26,Billing!B32,DailyAccomplishmentReport!$C$12:$C$26) -> 0 | D32: =SUMIF(DailyAccomplishmentReport!$B$12:$B$26,Billing!B32,DailyAccomplishmentReport!$AP$12:$AP$26) -> 0 | E32: =$E$10*C32 -> 0 | F32: =IFERROR($E$10*S32*D32,0) -> 0 | G32: =F32+E32 -> 0 | S32: =VLOOKUP(T32,Ref!$C$3:$D$14,2,FALSE) -> #VALUE! | T32: =VLOOKUP(B32,Ref!$F$3:$H$367,3,FALSE) -> #VALUE! | U32: =SUMIF(DailyAccomplishmentReport!$B$12:$B$43,Billing!B32,DailyAccomplishmentReport!$C$12:$C$43) -> 0
B33: =B32+1 -> #VALUE! | C33: =SUMIF(DailyAccomplishmentReport!$B$12:$B$26,Billing!B33,DailyAccomplishmentReport!$C$12:$C$26) -> 0 | D33: =SUMIF(DailyAccomplishmentReport!$B$12:$B$26,Billing!B33,DailyAccomplishmentReport!$AP$12:$AP$26) -> 0 | E33: =$E$10*C33 -> 0 | F33: =IFERROR($E$10*S33*D33,0) -> 0 | G33: =F33+E33 -> 0 | S33: =VLOOKUP(T33,Ref!$C$3:$D$14,2,FALSE) -> #VALUE! | T33: =VLOOKUP(B33,Ref!$F$3:$H$367,3,FALSE) -> #VALUE! | U33: =SUMIF(DailyAccomplishmentReport!$B$12:$B$43,Billing!B33,DailyAccomplishmentReport!$C$12:$C$43) -> 0
B34: =B33+1 -> #VALUE! | C34: =SUMIF(DailyAccomplishmentReport!$B$12:$B$26,Billing!B34,DailyAccomplishmentReport!$C$12:$C$26) -> 0 | D34: =SUMIF(DailyAccomplishmentReport!$B$12:$B$26,Billing!B34,DailyAccomplishmentReport!$AP$12:$AP$26) -> 0 | E34: =$E$10*C34 -> 0 | F34: =IFERROR($E$10*S34*D34,0) -> 0 | G34: =F34+E34 -> 0 | S34: =VLOOKUP(T34,Ref!$C$3:$D$14,2,FALSE) -> #VALUE! | T34: =VLOOKUP(B34,Ref!$F$3:$H$367,3,FALSE) -> #VALUE! | U34: =SUMIF(DailyAccomplishmentReport!$B$12:$B$43,Billing!B34,DailyAccomplishmentReport!$C$12:$C$43) -> 0
... B37: =B36+1 -> #VALUE! | C37: =SUMIF(DailyAccomplishmentReport!$B$12:$B$26,Billing!B37,DailyAccomplishmentReport!$C$12:$C$26) -> 0 | D37: =SUMIF(DailyAccomplishmentReport!$B$12:$B$26,Billing!B37,DailyAccomplishmentReport!$AP$12:$AP$26) -> 0 | E37: =$E$10*C37 -> 0 | F37: =IFERROR($E$10*S37*D37,0) -> 0 | G37: =F37+E37 -> 0 | S37: =VLOOKUP(T37,Ref!$C$3:$D$14,2,FALSE) -> #VALUE! | T37: =VLOOKUP(B37,Ref!$F$3:$H$367,3,FALSE) -> #VALUE! | U37: =SUMIF(DailyAccomplishmentReport!$B$12:$B$43,Billing!B37,DailyAccomplishmentReport!$C$12:$C$43) -> 0
B38: =B37+1 -> #VALUE! | C38: =SUMIF(DailyAccomplishmentReport!$B$12:$B$26,Billing!B38,DailyAccomplishmentReport!$C$12:$C$26) -> 0 | D38: =SUMIF(DailyAccomplishmentReport!$B$12:$B$26,Billing!B38,DailyAccomplishmentReport!$AP$12:$AP$26) -> 0 | E38: =$E$10*C38 -> 0 | F38: =IFERROR($E$10*S38*D38,0) -> 0 | G38: =F38+E38 -> 0
B39: =B38+1 -> #VALUE! | C39: =SUMIF(DailyAccomplishmentReport!$B$12:$B$26,Billing!B39,DailyAccomplishmentReport!$C$12:$C$26) -> 0 | D39: =SUMIF(DailyAccomplishmentReport!$B$12:$B$26,Billing!B39,DailyAccomplishmentReport!$AP$12:$AP$26) -> 0 | E39: =$E$10*C39 -> 0 | F39: =IFERROR($E$10*S39*D39,0) -> 0 | G39: =F39+E39 -> 0
B40: =B39+1 -> #VALUE! | C40: =SUMIF(DailyAccomplishmentReport!$B$12:$B$26,Billing!B40,DailyAccomplishmentReport!$C$12:$C$26) -> 0 | D40: =SUMIF(DailyAccomplishmentReport!$B$12:$B$26,Billing!B40,DailyAccomplishmentReport!$AP$12:$AP$26) -> 0 | E40: =$E$10*C40 -> 0 | F40: =IFERROR($E$10*S40*D40,0) -> 0 | G40: =F40+E40 -> 0
B41: =B40+1 -> #VALUE! | C41: =SUMIF(DailyAccomplishmentReport!$B$12:$B$26,Billing!B41,DailyAccomplishmentReport!$C$12:$C$26) -> 0 | D41: =SUMIF(DailyAccomplishmentReport!$B$12:$B$26,Billing!B41,DailyAccomplishmentReport!$AP$12:$AP$26) -> 0 | E41: =$E$10*C41 -> 0 | F41: =IFERROR($E$10*S41*D41,0) -> 0 | G41: =F41+E41 -> 0
B42: =B41+1 -> #VALUE! | C42: =SUMIF(DailyAccomplishmentReport!$B$12:$B$26,Billing!B42,DailyAccomplishmentReport!$C$12:$C$26) -> 0 | D42: =SUMIF(DailyAccomplishmentReport!$B$12:$B$26,Billing!B42,DailyAccomplishmentReport!$AP$12:$AP$26) -> 0 | E42: =$E$10*C42 -> 0 | F42: =IFERROR($E$10*S42*D42,0) -> 0 | G42: =F42+E42 -> 0
B43: =B42+1 -> #VALUE! | C43: =SUMIF(DailyAccomplishmentReport!$B$12:$B$26,Billing!B43,DailyAccomplishmentReport!$C$12:$C$26) -> 0 | D43: =SUMIF(DailyAccomplishmentReport!$B$12:$B$26,Billing!B43,DailyAccomplishmentReport!$AP$12:$AP$26) -> 0 | E43: =$E$10*C43 -> 0 | F43: =IFERROR($E$10*S43*D43,0) -> 0 | G43: =F43+E43 -> 0
B44: =B43+1 -> #VALUE! | C44: =SUMIF(DailyAccomplishmentReport!$B$12:$B$26,Billing!B44,DailyAccomplishmentReport!$C$12:$C$26) -> 0 | D44: =SUMIF(DailyAccomplishmentReport!$B$12:$B$26,Billing!B44,DailyAccomplishmentReport!$AP$12:$AP$26) -> 0 | E44: =$E$10*C44 -> 0 | F44: =IFERROR($E$10*S44*D44,0) -> 0 | G44: =F44+E44 -> 0
B45: =B44+1 -> #VALUE! | C45: =SUMIF(DailyAccomplishmentReport!$B$12:$B$26,Billing!B45,DailyAccomplishmentReport!$C$12:$C$26) -> 0 | D45: =SUMIF(DailyAccomplishmentReport!$B$12:$B$26,Billing!B45,DailyAccomplishmentReport!$AP$12:$AP$26) -> 0 | E45: =$E$10*C45 -> 0 | F45: =IFERROR($E$10*S45*D45,0) -> 0 | G45: =F45+E45 -> 0
B46: =B45+1 -> #VALUE! | C46: =SUMIF(DailyAccomplishmentReport!$B$12:$B$26,Billing!B46,DailyAccomplishmentReport!$C$12:$C$26) -> 0 | D46: =SUMIF(DailyAccomplishmentReport!$B$12:$B$26,Billing!B46,DailyAccomplishmentReport!$AP$12:$AP$26) -> 0 | E46: =$E$10*C46 -> 0 | F46: =IFERROR($E$10*S46*D46,0) -> 0 | G46: =F46+E46 -> 0
B47: =B46+1 -> #VALUE! | C47: =SUMIF(DailyAccomplishmentReport!$B$12:$B$26,Billing!B47,DailyAccomplishmentReport!$C$12:$C$26) -> 0 | D47: =SUMIF(DailyAccomplishmentReport!$B$12:$B$26,Billing!B47,DailyAccomplishmentReport!$AP$12:$AP$26) -> 0 | E47: =$E$10*C47 -> 0 | F47: =IFERROR($E$10*S47*D47,0) -> 0 | G47: =F47+E47 -> 0
B48: =B47+1 -> #VALUE! | C48: =SUMIF(DailyAccomplishmentReport!$B$12:$B$26,Billing!B48,DailyAccomplishmentReport!$C$12:$C$26) -> 0 | D48: =SUMIF(DailyAccomplishmentReport!$B$12:$B$26,Billing!B48,DailyAccomplishmentReport!$AP$12:$AP$26) -> 0 | E48: =$E$10*C48 -> 0 | F48: =IFERROR($E$10*S48*D48,0) -> 0 | G48: =F48+E48 -> 0
B49: =B48+1 -> #VALUE! | C49: =SUMIF(DailyAccomplishmentReport!$B$12:$B$26,Billing!B49,DailyAccomplishmentReport!$C$12:$C$26) -> 0 | D49: =SUMIF(DailyAccomplishmentReport!$B$12:$B$26,Billing!B49,DailyAccomplishmentReport!$AP$12:$AP$26) -> 0 | E49: =$E$10*C49 -> 0 | F49: =IFERROR($E$10*S49*D49,0) -> 0 | G49: =F49+E49 -> 0
... B52: =B51+1 -> #VALUE! | C52: =SUMIF(DailyAccomplishmentReport!$B$12:$B$26,Billing!B52,DailyAccomplishmentReport!$C$12:$C$26) -> 0 | D52: =SUMIF(DailyAccomplishmentReport!$B$12:$B$26,Billing!B52,DailyAccomplishmentReport!$AP$12:$AP$26) -> 0 | E52: =$E$10*C52 -> 0 | F52: =IFERROR($E$10*S52*D52,0) -> 0 | G52: =F52+E52 -> 0
B55: Total | C55: =SUM(C22:C53) -> 0 | D55: =SUM(D22:D53) -> 0 | E55: =SUM(E22:E53) -> 0 | F55: =SUM(F22:F53) -> 0 | G55: =SUM(G22:G53) -> 0
I58: TOTAL NUMBER OF WORKING HOURS PER SIR
I59: SIR Number | J59: Number of Hours
J60: Used | K60: Remaining | L60: OT % | M60: Total Man Hrs
J61: =SUMIF(DailyAccomplishmentReport!$E$12:$E$26,Billing!I61,DailyAccomplishmentReport!$C$12:$C$26) -> 0 | K61: =M61-J61 -> 0
J62: =SUMIF(DailyAccomplishmentReport!$E$12:$E$26,Billing!I62,DailyAccomplishmentReport!$C$12:$C$26) -> 0 | K62: =M62-J62 -> 0
J63: =SUMIF(DailyAccomplishmentReport!$E$12:$E$26,Billing!I63,DailyAccomplishmentReport!$C$12:$C$26) -> 0 | K63: =M63-J63 -> 0
J64: =SUMIF(DailyAccomplishmentReport!$E$12:$E$26,Billing!I64,DailyAccomplishmentReport!$C$12:$C$26) -> 0 | K64: =M64-J64 -> 0
J65: =SUMIF(DailyAccomplishmentReport!$E$12:$E$26,Billing!I65,DailyAccomplishmentReport!$C$12:$C$26) -> 0 | K65: =M65-J65 -> 0
J66: =SUMIF(DailyAccomplishmentReport!$E$12:$E$26,Billing!I66,DailyAccomplishmentReport!$C$12:$C$26) -> 0 | K66: =M66-J66 -> 0
J67: =SUMIF(DailyAccomplishmentReport!$E$12:$E$26,Billing!I67,DailyAccomplishmentReport!$C$12:$C$26) -> 0 | K67: =M67-J67 -> 0
J68: =SUMIF(DailyAccomplishmentReport!$E$12:$E$26,Billing!I68,DailyAccomplishmentReport!$C$12:$C$26) -> 0 | K68: =M68-J68 -> 0
J69: =SUMIF(DailyAccomplishmentReport!$E$12:$E$26,Billing!I69,DailyAccomplishmentReport!$C$12:$C$26) -> 0 | K69: =M69-J69 -> 0
J70: =SUMIF(DailyAccomplishmentReport!$E$12:$E$26,Billing!I70,DailyAccomplishmentReport!$C$12:$C$26) -> 0 | K70: =M70-J70 -> 0
J71: =SUMIF(DailyAccomplishmentReport!$E$12:$E$26,Billing!I71,DailyAccomplishmentReport!$C$12:$C$26) -> 0 | K71: =M71-J71 -> 0
J72: =SUMIF(DailyAccomplishmentReport!$E$12:$E$26,Billing!I72,DailyAccomplishmentReport!$C$12:$C$26) -> 0 | K72: =M72-J72 -> 0
... J82: =SUMIF(DailyAccomplishmentReport!$E$12:$E$26,Billing!I82,DailyAccomplishmentReport!$C$12:$C$26) -> 0 | K82: =M82-J82 -> 0

Sheet Ref
B2: Days | C2: Day Num | D2: Percent | F2: Date | G2: Days | H2: Day Num | I2: Holidays | K2: Provider | L2: Team Lead | M2: Section | N2: Activity | O2: Cost Center | P2: Budget to be Drawn From
B3: Weekdays | C3: 6 | D3: 1.25 | F3: 44197 | G3: =TEXT(F3,"ddd") -> Fri | H3: 97 | I3: New Year's Day | K3: SLI CONSULTING, INC. | L3: Ma. Corazon O. de Jesus | M3: BAS1 | N3: SIR - FS Analysis & Documentation | O3: Group Human Capital | P3: SIBS Enhancement
B4: Sunday | C4: 1 | D4: 1.3 | F4: =F3+1 -> 44198 | G4: =TEXT(F4,"ddd") -> Sat | H4: =IF(G4="Sun",1,IF(G4="Sat",7,6)) -> 7 | K4: Radix | L4: Jose Cabungcal | M4: BAS2 | N4: SIR - FS Review & Revision | O4: OP - Audit | P4: FRP
B5: Saturday | C5: 7 | D5: 1.25 | F5: =F4+1 -> 44199 | G5: =TEXT(F5,"ddd") -> Sun | H5: =IF(G5="Sun",1,IF(G5="Sat",7,6)) -> 1 | K5: Archon | L5: Catherine Ann Dequito | M5: BAS3 | N5: SIR - Development & Testing | O5: OP - Risk Mgmnt | P5: RMBP
B6: Special Holidays (Mon-Sat) | C6: 87 | D6: 1.3 | F6: =F5+1 -> 44200 | G6: =TEXT(F6,"ddd") -> Mon | H6: =IF(G6="Sun",1,IF(G6="Sat",7,6)) -> 6 | L6: Jesus Antonio Reyes | N6: SIR - SIT | O6: OP - Credit Mgmnt | P6: SIR Credit Cards
B7: Beyond SH (Mon-Sat) | C7: 887 | D7: 1.69 | F7: =F6+1 -> 44201 | G7: =TEXT(F7,"ddd") -> Tue | H7: =IF(G7="Sun",1,IF(G7="Sat",7,6)) -> 6 | L7: Jeffrey dela Peña | N7: SIR - UAT Support | O7: OP - IT
B8: Special Holidays(Sun) | C8: 81 | D8: 1.5 | F8: =F7+1 -> 44202 | G8: =TEXT(F8,"ddd") -> Wed | H8: =IF(G8="Sun",1,IF(G8="Sat",7,6)) -> 6 | L8: Ferdinand Blando | N8: Job Request | O8: OP - CorPLan
B9: Beyond SH (Sun) | C9: 881 | D9: 1.95 | F9: =F8+1 -> 44203 | G9: =TEXT(F9,"ddd") -> Thu | H9: =IF(G9="Sun",1,IF(G9="Sat",7,6)) -> 6 | N9: Assist BAS | O9: RBG - BE
B10: Legal Holidays (Mon-Sat) | C10: 97 | D10: 2 | F10: =F9+1 -> 44204 | G10: =TEXT(F10,"ddd") -> Fri | H10: =IF(G10="Sun",1,IF(G10="Sat",7,6)) -> 6 | N10: Production Issue/Problem | O10: RBG - QA
B11: Beyond LH (Mon-Sat) | C11: 997 | D11: 2.6 | F11: =F10+1 -> 44205 | G11: =TEXT(F11,"ddd") -> Sat | H11: =IF(G11="Sun",1,IF(G11="Sat",7,6)) -> 7 | N11: Production Support | O11: RBG - Business Dev
B12: Legal Holidays(Sun) | C12: 91 | D12: 2.6 | F12: =F11+1 -> 44206 | G12: =TEXT(F12,"ddd") -> Sun | H12: =IF(G12="Sun",1,IF(G12="Sat",7,6)) -> 1 | N12: Project Meeting | O12: RBG - VB
B13: Beyond LH (Sun) | C13: 991 | D13: 3.38 | F13: =F12+1 -> 44207 | G13: =TEXT(F13,"ddd") -> Mon | H13: =IF(G13="Sun",1,IF(G13="Sat",7,6)) -> 6 | N13: Training/Seminar | O13: RBG - Auto
B14: Night Shift | C14: 88 | D14: 0.1 | F14: =F13+1 -> 44208 | G14: =TEXT(F14,"ddd") -> Tue | H14: =IF(G14="Sun",1,IF(G14="Sat",7,6)) -> 6 | N14: Re-development | O14: RBG - Mortgage
F15: =F14+1 -> 44209 | G15: =TEXT(F15,"ddd") -> Wed | H15: =IF(G15="Sun",1,IF(G15="Sat",7,6)) -> 6 | N15: Others | O15: RBG - LAD(P/S)
F16: =F15+1 -> 44210 | G16: =TEXT(F16,"ddd") -> Thu | H16: =IF(G16="Sun",1,IF(G16="Sat",7,6)) -> 6 | O16: RBG - Cards
F17: =F16+1 -> 44211 | G17: =TEXT(F17,"ddd") -> Fri | H17: =IF(G17="Sun",1,IF(G17="Sat",7,6)) -> 6 | O17: RBG - CUL
F18: =F17+1 -> 44212 | G18: =TEXT(F18,"ddd") -> Sat | H18: =IF(G18="Sun",1,IF(G18="Sat",7,6)) -> 7 | L18: Department Head | O18: RBG - PL
F19: =F18+1 -> 44213 | G19: =TEXT(F19,"ddd") -> Sun | H19: =IF(G19="Sun",1,IF(G19="Sat",7,6)) -> 1 | L19: Lucy F. Espiritu | O19: RBG - CRM
F20: =F19+1 -> 44214 | G20: =TEXT(F20,"ddd") -> Mon | H20: =IF(G20="Sun",1,IF(G20="Sat",7,6)) -> 6 | O20: IAM - Global
F21: =F20+1 -> 44215 | G21: =TEXT(F21,"ddd") -> Tue | H21: =IF(G21="Sun",1,IF(G21="Sat",7,6)) -> 6 | O21: IAM - Trust
F22: =F21+1 -> 44216 | G22: =TEXT(F22,"ddd") -> Wed | H22: =IF(G22="Sun",1,IF(G22="Sat",7,6)) -> 6 | O22: COG - GMOS
F23: =F22+1 -> 44217 | G23: =TEXT(F23,"ddd") -> Thu | H23: =IF(G23="Sun",1,IF(G23="Sat",7,6)) -> 6 | O23: COG - BPM
F24: =F23+1 -> 44218 | G24: =TEXT(F24,"ddd") -> Fri | H24: =IF(G24="Sun",1,IF(G24="Sat",7,6)) -> 6 | O24: COG - ATM
F25: =F24+1 -> 44219 | G25: =TEXT(F25,"ddd") -> Sat | H25: =IF(G25="Sun",1,IF(G25="Sat",7,6)) -> 7 | O25: COG - CMS
F26: =F25+1 -> 44220 | G26: =TEXT(F26,"ddd") -> Sun | H26: =IF(G26="Sun",1,IF(G26="Sat",7,6)) -> 1 | O26: COG - Clearing
F27: =F26+1 -> 44221 | G27: =TEXT(F27,"ddd") -> Mon | H27: =IF(G27="Sun",1,IF(G27="Sat",7,6)) -> 6 | O27: COG - LAD
F28: =F27+1 -> 44222 | G28: =TEXT(F28,"ddd") -> Tue | H28: =IF(G28="Sun",1,IF(G28="Sat",7,6)) -> 6 | O28: COG - Remedial
F29: =F28+1 -> 44223 | G29: =TEXT(F29,"ddd") -> Wed | H29: =IF(G29="Sun",1,IF(G29="Sat",7,6)) -> 6 | O29: COG - Remittance
F30: =F29+1 -> 44224 | G30: =TEXT(F30,"ddd") -> Thu | H30: =IF(G30="Sun",1,IF(G30="Sat",7,6)) -> 6 | O30: COG - Trade
F31: =F30+1 -> 44225 | G31: =TEXT(F31,"ddd") -> Fri | H31: =IF(G31="Sun",1,IF(G31="Sat",7,6)) -> 6 | O31: Services - Accntg
... F44: =F43+1 -> 44238 | G44: =TEXT(F44,"ddd") -> Thu | H44: =IF(G44="Sun",1,IF(G44="Sat",7,6)) -> 6 | O44: RISK Mgmt. - CIAD
F45: =F44+1 -> 44239 | G45: =TEXT(F45,"ddd") -> Fri | H45: 87 | I45: Chinese New Year's Day
F46: =F45+1 -> 44240 | G46: =TEXT(F46,"ddd") -> Sat | H46: =IF(G46="Sun",1,IF(G46="Sat",7,6)) -> 7
F47: =F46+1 -> 44241 | G47: =TEXT(F47,"ddd") -> Sun | H47: =IF(G47="Sun",1,IF(G47="Sat",7,6)) -> 1
F48: =F47+1 -> 44242 | G48: =TEXT(F48,"ddd") -> Mon | H48: =IF(G48="Sun",1,IF(G48="Sat",7,6)) -> 6
F49: =F48+1 -> 44243 | G49: =TEXT(F49,"ddd") -> Tue | H49: =IF(G49="Sun",1,IF(G49="Sat",7,6)) -> 6
F50: =F49+1 -> 44244 | G50: =TEXT(F50,"ddd") -> Wed | H50: =IF(G50="Sun",1,IF(G50="Sat",7,6)) -> 6
F51: =F50+1 -> 44245 | G51: =TEXT(F51,"ddd") -> Thu | H51: =IF(G51="Sun",1,IF(G51="Sat",7,6)) -> 6
F52: =F51+1 -> 44246 | G52: =TEXT(F52,"ddd") -> Fri | H52: =IF(G52="Sun",1,IF(G52="Sat",7,6)) -> 6
F53: =F52+1 -> 44247 | G53: =TEXT(F53,"ddd") -> Sat | H53: =IF(G53="Sun",1,IF(G53="Sat",7,6)) -> 7
F54: =F53+1 -> 44248 | G54: =TEXT(F54,"ddd") -> Sun | H54: =IF(G54="Sun",1,IF(G54="Sat",7,6)) -> 1
F55: =F54+1 -> 44249 | G55: =TEXT(F55,"ddd") -> Mon | H55: =IF(G55="Sun",1,IF(G55="Sat",7,6)) -> 6
F56: =F55+1 -> 44250 | G56: =TEXT(F56,"ddd") -> Tue | H56: =IF(G56="Sun",1,IF(G56="Sat",7,6)) -> 6
F57: =F56+1 -> 44251 | G57: =TEXT(F57,"ddd") -> Wed | H57: =IF(G57="Sun",1,IF(G57="Sat",7,6)) -> 6
F58: =F57+1 -> 44252 | G58: =TEXT(F58,"ddd") -> Thu | H58: 87 | I58: EDSA People Power Revolution Anniversary
F59: =F58+1 -> 44253 | G59: =TEXT(F59,"ddd") -> Fri | H59: =IF(G59="Sun",1,IF(G59="Sat",7,6)) -> 6
F60: =F59+1 -> 44254 | G60: =TEXT(F60,"ddd") -> Sat | H60: =IF(G60="Sun",1,IF(G60="Sat",7,6)) -> 7
F61: =F60+1 -> 44255 | G61: =TEXT(F61,"ddd") -> Sun | H61: =IF(G61="Sun",1,IF(G61="Sat",7,6)) -> 1
F62: =F61+1 -> 44256 | G62: =TEXT(F62,"ddd") -> Mon | H62: =IF(G62="Sun",1,IF(G62="Sat",7,6)) -> 6
F63: =F62+1 -> 44257 | G63: =TEXT(F63,"ddd") -> Tue | H63: =IF(G63="Sun",1,IF(G63="Sat",7,6)) -> 6
F64: =F63+1 -> 44258 | G64: =TEXT(F64,"ddd") -> Wed | H64: =IF(G64="Sun",1,IF(G64="Sat",7,6)) -> 6
F65: =F64+1 -> 44259 | G65: =TEXT(F65,"ddd") -> Thu | H65: =IF(G65="Sun",1,IF(G65="Sat",7,6)) -> 6
F66: =F65+1 -> 44260 | G66: =TEXT(F66,"ddd") -> Fri | H66: =IF(G66="Sun",1,IF(G66="Sat",7,6)) -> 6
F67: =F66+1 -> 44261 | G67: =TEXT(F67,"ddd") -> Sat | H67: =IF(G67="Sun",1,IF(G67="Sat",7,6)) -> 7
F68: =F67+1 -> 44262 | G68: =TEXT(F68,"ddd") -> Sun | H68: =IF(G68="Sun",1,IF(G68="Sat",7,6)) -> 1
F69: =F68+1 -> 44263 | G69: =TEXT(F69,"ddd") -> Mon | H69: =IF(G69="Sun",1,IF(G69="Sat",7,6)) -> 6
F70: =F69+1 -> 44264 | G70: =TEXT(F70,"ddd") -> Tue | H70: =IF(G70="Sun",1,IF(G70="Sat",7,6)) -> 6
... F92: =F91+1 -> 44286 | G92: =TEXT(F92,"ddd") -> Wed | H92: =IF(G92="Sun",1,IF(G92="Sat",7,6)) -> 6
F93: =F92+1 -> 44287 | G93: =TEXT(F93,"ddd") -> Thu | H93: 97 | I93: Maundy Thursday
F94: =F93+1 -> 44288 | G94: =TEXT(F94,"ddd") -> Fri | H94: 97 | I94: Good Friday
F95: =F94+1 -> 44289 | G95: =TEXT(F95,"ddd") -> Sat | H95: 87 | I95: Black Saturday
F96: =F95+1 -> 44290 | G96: =TEXT(F96,"ddd") -> Sun | H96: =IF(G96="Sun",1,IF(G96="Sat",7,6)) -> 1
F97: =F96+1 -> 44291 | G97: =TEXT(F97,"ddd") -> Mon | H97: =IF(G97="Sun",1,IF(G97="Sat",7,6)) -> 6
F98: =F97+1 -> 44292 | G98: =TEXT(F98,"ddd") -> Tue | H98: =IF(G98="Sun",1,IF(G98="Sat",7,6)) -> 6
F99: =F98+1 -> 44293 | G99: =TEXT(F99,"ddd") -> Wed | H99: =IF(G99="Sun",1,IF(G99="Sat",7,6)) -> 6
F100: =F99+1 -> 44294 | G100: =TEXT(F100,"ddd") -> Thu | H100: =IF(G100="Sun",1,IF(G100="Sat",7,6)) -> 6
F101: =F100+1 -> 44295 | G101: =TEXT(F101,"ddd") -> Fri | H101: 6
F102: =F101+1 -> 44296 | G102: =TEXT(F102,"ddd") -> Sat | H102: 97 | I102: Araw ng Kagitingan
F103: =F102+1 -> 44297 | G103: =TEXT(F103,"ddd") -> Sun | H103: =IF(G103="Sun",1,IF(G103="Sat",7,6)) -> 1
F104: =F103+1 -> 44298 | G104: =TEXT(F104,"ddd") -> Mon | H104: =IF(G104="Sun",1,IF(G104="Sat",7,6)) -> 6
F105: =F104+1 -> 44299 | G105: =TEXT(F105,"ddd") -> Tue | H105: =IF(G105="Sun",1,IF(G105="Sat",7,6)) -> 6
F106: =F105+1 -> 44300 | G106: =TEXT(F106,"ddd") -> Wed | H106: =IF(G106="Sun",1,IF(G106="Sat",7,6)) -> 6
F107: =F106+1 -> 44301 | G107: =TEXT(F107,"ddd") -> Thu | H107: =IF(G107="Sun",1,IF(G107="Sat",7,6)) -> 6
F108: =F107+1 -> 44302 | G108: =TEXT(F108,"ddd") -> Fri | H108: =IF(G108="Sun",1,IF(G108="Sat",7,6)) -> 6
F109: =F108+1 -> 44303 | G109: =TEXT(F109,"ddd") -> Sat | H109: =IF(G109="Sun",1,IF(G109="Sat",7,6)) -> 7
F110: =F109+1 -> 44304 | G110: =TEXT(F110,"ddd") -> Sun | H110: =IF(G110="Sun",1,IF(G110="Sat",7,6)) -> 1
F111: =F110+1 -> 44305 | G111: =TEXT(F111,"ddd") -> Mon | H111: =IF(G111="Sun",1,IF(G111="Sat",7,6)) -> 6
F112: =F111+1 -> 44306 | G112: =TEXT(F112,"ddd") -> Tue | H112: =IF(G112="Sun",1,IF(G112="Sat",7,6)) -> 6
F113: =F112+1 -> 44307 | G113: =TEXT(F113,"ddd") -> Wed | H113: =IF(G113="Sun",1,IF(G113="Sat",7,6)) -> 6
F114: =F113+1 -> 44308 | G114: =TEXT(F114,"ddd") -> Thu | H114: =IF(G114="Sun",1,IF(G114="Sat",7,6)) -> 6
... F122: =F121+1 -> 44316 | G122: =TEXT(F122,"ddd") -> Fri | H122: =IF(G122="Sun",1,IF(G122="Sat",7,6)) -> 6
F123: =F122+1 -> 44317 | G123: =TEXT(F123,"ddd") -> Sat | H123: 97 | I123: Labor's Day
F124: =F123+1 -> 44318 | G124: =TEXT(F124,"ddd") -> Sun | H124: =IF(G124="Sun",1,IF(G124="Sat",7,6)) -> 1
F125: =F124+1 -> 44319 | G125: =TEXT(F125,"ddd") -> Mon | H125: =IF(G125="Sun",1,IF(G125="Sat",7,6)) -> 6
F126: =F125+1 -> 44320 | G126: =TEXT(F126,"ddd") -> Tue | H126: =IF(G126="Sun",1,IF(G126="Sat",7,6)) -> 6
F127: =F126+1 -> 44321 | G127: =TEXT(F127,"ddd") -> Wed | H127: =IF(G127="Sun",1,IF(G127="Sat",7,6)) -> 6
F128: =F127+1 -> 44322 | G128: =TEXT(F128,"ddd") -> Thu | H128: =IF(G128="Sun",1,IF(G128="Sat",7,6)) -> 6
F129: =F128+1 -> 44323 | G129: =TEXT(F129,"ddd") -> Fri | H129: =IF(G129="Sun",1,IF(G129="Sat",7,6)) -> 6
F130: =F129+1 -> 44324 | G130: =TEXT(F130,"ddd") -> Sat | H130: =IF(G130="Sun",1,IF(G130="Sat",7,6)) -> 7
F131: =F130+1 -> 44325 | G131: =TEXT(F131,"ddd") -> Sun | H131: =IF(G131="Sun",1,IF(G131="Sat",7,6)) -> 1
F132: =F131+1 -> 44326 | G132: =TEXT(F132,"ddd") -> Mon | H132: =IF(G132="Sun",1,IF(G132="Sat",7,6)) -> 6
F133: =F132+1 -> 44327 | G133: =TEXT(F133,"ddd") -> Tue | H133: =IF(G133="Sun",1,IF(G133="Sat",7,6)) -> 6
F134: =F133+1 -> 44328 | G134: =TEXT(F134,"ddd") -> Wed | H134: =IF(G134="Sun",1,IF(G134="Sat",7,6)) -> 6
F135: =F134+1 -> 44329 | G135: =TEXT(F135,"ddd") -> Thu | H135: =IF(G135="Sun",1,IF(G135="Sat",7,6)) -> 6
... F164: =F163+1 -> 44358 | G164: =TEXT(F164,"ddd") -> Fri | H164: =IF(G164="Sun",1,IF(G164="Sat",7,6)) -> 6
F165: =F164+1 -> 44359 | G165: =TEXT(F165,"ddd") -> Sat | H165: 97 | I165: Independence Day
F166: =F165+1 -> 44360 | G166: =TEXT(F166,"ddd") -> Sun | H166: =IF(G166="Sun",1,IF(G166="Sat",7,6)) -> 1
F167: =F166+1 -> 44361 | G167: =TEXT(F167,"ddd") -> Mon | H167: =IF(G167="Sun",1,IF(G167="Sat",7,6)) -> 6
F168: =F167+1 -> 44362 | G168: =TEXT(F168,"ddd") -> Tue | H168: =IF(G168="Sun",1,IF(G168="Sat",7,6)) -> 6
F169: =F168+1 -> 44363 | G169: =TEXT(F169,"ddd") -> Wed | H169: =IF(G169="Sun",1,IF(G169="Sat",7,6)) -> 6
...

Sheet Summary
B1: DTR Summary
B3: Cost Center | C3: Budget To Be Drawn Form | D3: Regular Hrs | E3: OT Hrs | F3: Regular(Cost) | G3: OT(Cost) | H3: Total Cost | I3: 12% VAT | J3: Final Cost | K3: Hourly Rate | L3: VAT Rate
B4: =DailyAccomplishmentReport!S12 -> 0 | C4: =DailyAccomplishmentReport!T12 -> 0 | D4: =DailyAccomplishmentReport!C12 | E4: =DailyAccomplishmentReport!AP12 -> 0 | F4: =D4*$K$4 -> #VALUE! | G4: =E4*$K$4 -> 0 | H4: =F4+G4 -> #VALUE! | I4: =H4*$L$4 -> #VALUE! | J4: =H4+I4 -> #VALUE! | K4: =Billing!E10 -> 0 | L4: 0.12
B5: =DailyAccomplishmentReport!S13 -> 0 | C5: =DailyAccomplishmentReport!T13 -> 0 | D5: =DailyAccomplishmentReport!C13 | E5: =DailyAccomplishmentReport!AP13 -> 0 | F5: =D5*$K$4 -> #VALUE! | G5: =E5*$K$4 -> 0 | H5: =F5+G5 -> #VALUE! | I5: =H5*$L$4 -> #VALUE! | J5: =H5+I5 -> #VALUE!
B6: =DailyAccomplishmentReport!S14 -> OP - IT | C6: =DailyAccomplishmentReport!T14 -> 0 | D6: =DailyAccomplishmentReport!C14 -> 8 | E6: =DailyAccomplishmentReport!AP14 -> 0 | F6: =D6*$K$4 -> 0 | G6: =E6*$K$4 -> 0 | H6: =F6+G6 -> 0 | I6: =H6*$L$4 -> 0 | J6: =H6+I6 -> 0
B7: =DailyAccomplishmentReport!S15 -> OP - IT | C7: =DailyAccomplishmentReport!T15 -> 0 | D7: =DailyAccomplishmentReport!C15 -> 8 | E7: =DailyAccomplishmentReport!AP15 -> 0 | F7: =D7*$K$4 -> 0 | G7: =E7*$K$4 -> 0 | H7: =F7+G7 -> 0 | I7: =H7*$L$4 -> 0 | J7: =H7+I7 -> 0
B8: =DailyAccomplishmentReport!S16 -> OP - IT | C8: =DailyAccomplishmentReport!T16 -> 0 | D8: =DailyAccomplishmentReport!C16 -> 8 | E8: =DailyAccomplishmentReport!AP16 -> 0 | F8: =D8*$K$4 -> 0 | G8: =E8*$K$4 -> 0 | H8: =F8+G8 -> 0 | I8: =H8*$L$4 -> 0 | J8: =H8+I8 -> 0
B9: =DailyAccomplishmentReport!S17 -> OP - IT | C9: =DailyAccomplishmentReport!T17 -> 0 | D9: =DailyAccomplishmentReport!C17 -> 8 | E9: =DailyAccomplishmentReport!AP17 -> 0 | F9: =D9*$K$4 -> 0 | G9: =E9*$K$4 -> 0 | H9: =F9+G9 -> 0 | I9: =H9*$L$4 -> 0 | J9: =H9+I9 -> 0
B10: =DailyAccomplishmentReport!S18 -> OP - IT | C10: =DailyAccomplishmentReport!T18 -> 0 | D10: =DailyAccomplishmentReport!C18 -> 8 | E10: =DailyAccomplishmentReport!AP18 -> 0 | F10: =D10*$K$4 -> 0 | G10: =E10*$K$4 -> 0 | H10: =F10+G10 -> 0 | I10: =H10*$L$4 -> 0 | J10: =H10+I10 -> 0
B11: =DailyAccomplishmentReport!S19 -> 0 | C11: =DailyAccomplishmentReport!T19 -> 0 | D11: =DailyAccomplishmentReport!C19 | E11: =DailyAccomplishmentReport!AP19 -> 0 | F11: =D11*$K$4 -> #VALUE! | G11: =E11*$K$4 -> 0 | H11: =F11+G11 -> #VALUE! | I11: =H11*$L$4 -> #VALUE! | J11: =H11+I11 -> #VALUE!
B12: =DailyAccomplishmentReport!S20 -> 0 | C12: =DailyAccomplishmentReport!T20 -> 0 | D12: =DailyAccomplishmentReport!C20 | E12: =DailyAccomplishmentReport!AP20 -> 0 | F12: =D12*$K$4 -> #VALUE! | G12: =E12*$K$4 -> 0 | H12: =F12+G12 -> #VALUE! | I12: =H12*$L$4 -> #VALUE! | J12: =H12+I12 -> #VALUE!
B13: =DailyAccomplishmentReport!S21 -> 0 | C13: =DailyAccomplishmentReport!T21 -> 0 | D13: =DailyAccomplishmentReport!C21 | E13: =DailyAccomplishmentReport!AP21 -> 0 | F13: =D13*$K$4 -> #VALUE! | G13: =E13*$K$4 -> 0 | H13: =F13+G13 -> #VALUE! | I13: =H13*$L$4 -> #VALUE! | J13: =H13+I13 -> #VALUE!
B14: =DailyAccomplishmentReport!S22 -> OP - IT | C14: =DailyAccomplishmentReport!T22 -> 0 | D14: =DailyAccomplishmentReport!C22 -> 8 | E14: =DailyAccomplishmentReport!AP22 -> 0 | F14: =D14*$K$4 -> 0 | G14: =E14*$K$4 -> 0 | H14: =F14+G14 -> 0 | I14: =H14*$L$4 -> 0 | J14: =H14+I14 -> 0
B15: =DailyAccomplishmentReport!S23 -> OP - IT | C15: =DailyAccomplishmentReport!T23 -> 0 | D15: =DailyAccomplishmentReport!C23 -> 5.83 | E15: =DailyAccomplishmentReport!AP23 -> 0 | F15: =D15*$K$4 -> 0 | G15: =E15*$K$4 -> 0 | H15: =F15+G15 -> 0 | I15: =H15*$L$4 -> 0 | J15: =H15+I15 -> 0
B16: =DailyAccomplishmentReport!S24 -> OP - IT | C16: =DailyAccomplishmentReport!T24 -> 0 | D16: =DailyAccomplishmentReport!C24 -> 8 | E16: =DailyAccomplishmentReport!AP24 -> 0 | F16: =D16*$K$4 -> 0 | G16: =E16*$K$4 -> 0 | H16: =F16+G16 -> 0 | I16: =H16*$L$4 -> 0 | J16: =H16+I16 -> 0
B17: =DailyAccomplishmentReport!S25 -> OP - IT | C17: =DailyAccomplishmentReport!T25 -> 0 | D17: =DailyAccomplishmentReport!C25 -> 8 | E17: =DailyAccomplishmentReport!AP25 -> 0 | F17: =D17*$K$4 -> 0 | G17: =E17*$K$4 -> 0 | H17: =F17+G17 -> 0 | I17: =H17*$L$4 -> 0 | J17: =H17+I17 -> 0
B18: =DailyAccomplishmentReport!S27 -> 0 | C18: =DailyAccomplishmentReport!T26 -> 0 | D18: =DailyAccomplishmentReport!C26 | E18: =DailyAccomplishmentReport!AP26 -> 0 | F18: =D18*$K$4 -> #VALUE! | G18: =E18*$K$4 -> 0 | H18: =F18+G18 -> #VALUE! | I18: =H18*$L$4 -> #VALUE! | J18: =H18+I18 -> #VALUE!
B19: =DailyAccomplishmentReport!#REF! -> #REF! | C19: =DailyAccomplishmentReport!#REF! -> #REF! | D19: =DailyAccomplishmentReport!#REF! -> #REF! | E19: =DailyAccomplishmentReport!#REF! -> #REF! | F19: =D19*$K$4 -> #REF! | G19: =E19*$K$4 -> #REF! | H19: =F19+G19 -> #REF! | I19: =H19*$L$4 -> #REF! | J19: =H19+I19 -> #REF!
B20: =DailyAccomplishmentReport!#REF! -> #REF! | C20: =DailyAccomplishmentReport!#REF! -> #REF! | D20: =DailyAccomplishmentReport!#REF! -> #REF! | E20: =DailyAccomplishmentReport!#REF! -> #REF! | F20: =D20*$K$4 -> #REF! | G20: =E20*$K$4 -> #REF! | H20: =F20+G20 -> #REF! | I20: =H20*$L$4 -> #REF! | J20: =H20+I20 -> #REF!
B21: =DailyAccomplishmentReport!#REF! -> #REF! | C21: =DailyAccomplishmentReport!#REF! -> #REF! | D21: =DailyAccomplishmentReport!#REF! -> #REF! | E21: =DailyAccomplishmentReport!#REF! -> #REF! | F21: =D21*$K$4 -> #REF! | G21: =E21*$K$4 -> #REF! | H21: =F21+G21 -> #REF! | I21: =H21*$L$4 -> #REF! | J21: =H21+I21 -> #REF!
B22: =DailyAccomplishmentReport!#REF! -> #REF! | C22: =DailyAccomplishmentReport!#REF! -> #REF! | D22: =DailyAccomplishmentReport!#REF! -> #REF! | E22: =DailyAccomplishmentReport!#REF! -> #REF! | F22: =D22*$K$4 -> #REF! | G22: =E22*$K$4 -> #REF! | H22: =F22+G22 -> #REF! | I22: =H22*$L$4 -> #REF! | J22: =H22+I22 -> #REF!
B23: =DailyAccomplishmentReport!#REF! -> #REF! | C23: =DailyAccomplishmentReport!#REF! -> #REF! | D23: =DailyAccomplishmentReport!#REF! -> #REF! | E23: =DailyAccomplishmentReport!#REF! -> #REF! | F23: =D23*$K$4 -> #REF! | G23: =E23*$K$4 -> #REF! | H23: =F23+G23 -> #REF! | I23: =H23*$L$4 -> #REF! | J23: =H23+I23 -> #REF!
B24: =DailyAccomplishmentReport!#REF! -> #REF! | C24: =DailyAccomplishmentReport!#REF! -> #REF! | D24: =DailyAccomplishmentReport!#REF! -> #REF! | E24: =DailyAccomplishmentReport!#REF! -> #REF! | F24: =D24*$K$4 -> #REF! | G24: =E24*$K$4 -> #REF! | H24: =F24+G24 -> #REF! | I24: =H24*$L$4 -> #REF! | J24: =H24+I24 -> #REF!
B25: =DailyAccomplishmentReport!#REF! -> #REF! | C25: =DailyAccomplishmentReport!#REF! -> #REF! | D25: =DailyAccomplishmentReport!#REF! -> #REF! | E25: =DailyAccomplishmentReport!#REF! -> #REF! | F25: =D25*$K$4 -> #REF! | G25: =E25*$K$4 -> #REF! | H25: =F25+G25 -> #REF! | I25: =H25*$L$4 -> #REF! | J25: =H25+I25 -> #REF!
B26: =DailyAccomplishmentReport!#REF! -> #REF! | C26: =DailyAccomplishmentReport!#REF! -> #REF! | D26: =DailyAccomplishmentReport!#REF! -> #REF! | E26: =DailyAccomplishmentReport!#REF! -> #REF! | F26: =D26*$K$4 -> #REF! | G26: =E26*$K$4 -> #REF! | H26: =F26+G26 -> #REF! | I26: =H26*$L$4 -> #REF! | J26: =H26+I26 -> #REF!
B27: =DailyAccomplishmentReport!#REF! -> #REF! | C27: =DailyAccomplishmentReport!#REF! -> #REF! | D27: =DailyAccomplishmentReport!#REF! -> #REF! | E27: =DailyAccomplishmentReport!#REF! -> #REF! | F27: =D27*$K$4 -> #REF! | G27: =E27*$K$4 -> #REF! | H27: =F27+G27 -> #REF! | I27: =H27*$L$4 -> #REF! | J27: =H27+I27 -> #REF!
B28: =DailyAccomplishmentReport!#REF! -> #REF! | C28: =DailyAccomplishmentReport!#REF! -> #REF! | D28: =DailyAccomplishmentReport!#REF! -> #REF! | E28: =DailyAccomplishmentReport!#REF! -> #REF! | F28: =D28*$K$4 -> #REF! | G28: =E28*$K$4 -> #REF! | H28: =F28+G28 -> #REF! | I28: =H28*$L$4 -> #REF! | J28: =H28+I28 -> #REF!
B29: =DailyAccomplishmentReport!#REF! -> #REF! | C29: =DailyAccomplishmentReport!#REF! -> #REF! | D29: =DailyAccomplishmentReport!#REF! -> #REF! | E29: =DailyAccomplishmentReport!#REF! -> #REF! | F29: =D29*$K$4 -> #REF! | G29: =E29*$K$4 -> #REF! | H29: =F29+G29 -> #REF! | I29: =H29*$L$4 -> #REF! | J29: =H29+I29 -> #REF!
B30: =DailyAccomplishmentReport!#REF! -> #REF! | C30: =DailyAccomplishmentReport!#REF! -> #REF! | D30: =DailyAccomplishmentReport!#REF! -> #REF! | E30: =DailyAccomplishmentReport!#REF! -> #REF! | F30: =D30*$K$4 -> #REF! | G30: =E30*$K$4 -> #REF! | H30: =F30+G30 -> #REF! | I30: =H30*$L$4 -> #REF! | J30: =H30+I30 -> #REF!
B31: =DailyAccomplishmentReport!#REF! -> #REF! | C31: =DailyAccomplishmentReport!#REF! -> #REF! | D31: =#REF! -> #REF! | E31: =DailyAccomplishmentReport!#REF! -> #REF! | F31: =D31*$K$4 -> #REF! | G31: =E31*$K$4 -> #REF! | H31: =F31+G31 -> #REF! | I31: =H31*$L$4 -> #REF! | J31: =H31+I31 -> #REF!
B32: =DailyAccomplishmentReport!#REF! -> #REF! | C32: =DailyAccomplishmentReport!#REF! -> #REF! | D32: =DailyAccomplishmentReport!#REF! -> #REF! | E32: =DailyAccomplishmentReport!#REF! -> #REF! | F32: =D32*$K$4 -> #REF! | G32: =E32*$K$4 -> #REF! | H32: =F32+G32 -> #REF! | I32: =H32*$L$4 -> #REF! | J32: =H32+I32 -> #REF!
B33: =DailyAccomplishmentReport!#REF! -> #REF! | C33: =DailyAccomplishmentReport!#REF! -> #REF! | D33: =DailyAccomplishmentReport!#REF! -> #REF! | E33: =DailyAccomplishmentReport!#REF! -> #REF! | F33: =D33*$K$4 -> #REF! | G33: =E33*$K$4 -> #REF! | H33: =F33+G33 -> #REF! | I33: =H33*$L$4 -> #REF! | J33: =H33+I33 -> #REF!
B34: =DailyAccomplishmentReport!#REF! -> #REF! | C34: =DailyAccomplishmentReport!#REF! -> #REF! | D34: =DailyAccomplishmentReport!#REF! -> #REF! | E34: =DailyAccomplishmentReport!#REF! -> #REF! | F34: =D34*$K$4 -> #REF! | G34: =E34*$K$4 -> #REF! | H34: =F34+G34 -> #REF! | I34: =H34*$L$4 -> #REF! | J34: =H34+I34 -> #REF!
B35: =DailyAccomplishmentReport!#REF! -> #REF! | C35: =DailyAccomplishmentReport!#REF! -> #REF! | D35: =DailyAccomplishmentReport!#REF! -> #REF! | E35: =DailyAccomplishmentReport!#REF! -> #REF! | F35: =D35*$K$4 -> #REF! | G35: =E35*$K$4 -> #REF! | H35: =F35+G35 -> #REF! | I35: =H35*$L$4 -> #REF! | J35: =H35+I35 -> #REF!
B36: =DailyAccomplishmentReport!#REF! -> #REF! | C36: =DailyAccomplishmentReport!#REF! -> #REF! | D36: =DailyAccomplishmentReport!#REF! -> #REF! | E36: =DailyAccomplishmentReport!#REF! -> #REF! | F36: =D36*$K$4 -> #REF! | G36: =E36*$K$4 -> #REF! | H36: =F36+G36 -> #REF! | I36: =H36*$L$4 -> #REF! | J36: =H36+I36 -> #REF!
B37: =DailyAccomplishmentReport!#REF! -> #REF! | C37: =DailyAccomplishmentReport!#REF! -> #REF! | D37: =DailyAccomplishmentReport!#REF! -> #REF! | E37: =DailyAccomplishmentReport!#REF! -> #REF! | F37: =D37*$K$4 -> #REF! | G37: =E37*$K$4 -> #REF! | H37: =F37+G37 -> #REF! | I37: =H37*$L$4 -> #REF! | J37: =H37+I37 -> #REF!
B38: =DailyAccomplishmentReport!#REF! -> #REF! | C38: =DailyAccomplishmentReport!#REF! -> #REF! | D38: =DailyAccomplishmentReport!#REF! -> #REF! | E38: =DailyAccomplishmentReport!#REF! -> #REF! | F38: =D38*$K$4 -> #REF! | G38: =E38*$K$4 -> #REF! | H38: =F38+G38 -> #REF! | I38: =H38*$L$4 -> #REF! | J38: =H38+I38 -> #REF!
B39: =DailyAccomplishmentReport!#REF! -> #REF! | C39: =DailyAccomplishmentReport!#REF! -> #REF! | D39: =DailyAccomplishmentReport!#REF! -> #REF! | E39: =DailyAccomplishmentReport!#REF! -> #REF! | F39: =D39*$K$4 -> #REF! | G39: =E39*$K$4 -> #REF! | H39: =F39+G39 -> #REF! | I39: =H39*$L$4 -> #REF! | J39: =H39+I39 -> #REF!
B40: =DailyAccomplishmentReport!#REF! -> #REF! | C40: =DailyAccomplishmentReport!#REF! -> #REF! | D40: =DailyAccomplishmentReport!#REF! -> #REF! | E40: =DailyAccomplishmentReport!#REF! -> #REF! | F40: =D40*$K$4 -> #REF! | G40: =E40*$K$4 -> #REF! | H40: =F40+G40 -> #REF! | I40: =H40*$L$4 -> #REF! | J40: =H40+I40 -> #REF!
B41: =DailyAccomplishmentReport!#REF! -> #REF! | C41: =DailyAccomplishmentReport!#REF! -> #REF! | D41: =DailyAccomplishmentReport!#REF! -> #REF! | E41: =DailyAccomplishmentReport!#REF! -> #REF! | F41: =D41*$K$4 -> #REF! | G41: =E41*$K$4 -> #REF! | H41: =F41+G41 -> #REF! | I41: =H41*$L$4 -> #REF! | J41: =H41+I41 -> #REF!
B42: =DailyAccomplishmentReport!#REF! -> #REF! | C42: =DailyAccomplishmentReport!#REF! -> #REF! | D42: =DailyAccomplishmentReport!#REF! -> #REF! | E42: =DailyAccomplishmentReport!#REF! -> #REF! | F42: =D42*$K$4 -> #REF! | G42: =E42*$K$4 -> #REF! | H42: =F42+G42 -> #REF! | I42: =H42*$L$4 -> #REF! | J42: =H42+I42 -> #REF!
B43: =DailyAccomplishmentReport!#REF! -> #REF! | C43: =DailyAccomplishmentReport!#REF! -> #REF! | D43: =DailyAccomplishmentReport!#REF! -> #REF! | E43: =DailyAccomplishmentReport!#REF! -> #REF! | F43: =D43*$K$4 -> #REF! | G43: =E43*$K$4 -> #REF! | H43: =F43+G43 -> #REF! | I43: =H43*$L$4 -> #REF! | J43: =H43+I43 -> #REF!
... B92: =DailyAccomplishmentReport!#REF! -> #REF! | C92: =DailyAccomplishmentReport!#REF! -> #REF! | D92: =DailyAccomplishmentReport!#REF! -> #REF! | E92: =DailyAccomplishmentReport!#REF! -> #REF! | F92: =D92*$K$4 -> #REF! | G92: =E92*$K$4 -> #REF! | H92: =F92+G92 -> #REF! | I92: =H92*$L$4 -> #REF! | J92: =H92+I92 -> #REF!
B93: =DailyAccomplishmentReport!S43 -> 0 | C93: =DailyAccomplishmentReport!T43 -> 0 | D93: =DailyAccomplishmentReport!C43 -> 0 | E93: =DailyAccomplishmentReport!AP43 -> 0 | F93: =D93*$K$4 -> 0 | G93: =E93*$K$4 -> 0 | H93: =F93+G93 -> 0 | I93: =H93*$L$4 -> 0 | J93: =H93+I93 -> 0
